Workbook

Sheet LEAD
B2: XBRL CoE Checklist
B3: ※ XBRL Checklist 결과는 참고 목적으로 제공드리는 내역으로, 텍사노미 구조와 관련된 리뷰는 CoE 업무 Scope에 포함되지 않습니다.
B11: ="Total"&" : "&SUM(N14:N52) -> Total : 0 | C11: 개 항목이 추출되었습니다.
B13: # | C13: 항목 | D13: 세부내역 | N13: 검출항목
B14: 1 | C14: 특정요소 사용검토 | D14: • 총액계정 사용 검토 | N14: ='Checklist_1-1'!B11 -> 0
D15: • 초과적립액(과소적립액) | N15: ='Checklist_1-2'!B11 -> 0
D16: • 재고자산 세부내역 표 | N16: ='Checklist_1-3'!B11 -> 0
D17: • 유동/비유동 축 | N17: ='Checklist_1-4'!B11 -> 0
B18: 2 | C18: 택사노미 검토 | D18: • 금융자산의 대손충당금 (만료 텍사노미 검토) | N18: ='Checklist_2-1'!B11 -> 0
D19: • 금융자산의 손상차손 축 (만료 텍사노미 검토) | N19: ='Checklist_2-2'!B11 -> 0
D20: • 대출약정금액 텍사노미 검토 | N20: ='Checklist_2-3'!B11 -> 0
D21: • 미착품 택사노미 검토 | N21: ='Checklist_2-4'!B11 -> 0
D22: • 배당금 텍사노미 검토 | N22: ='Checklist_2-5'!$B$11 -> 0
D23: • 평균유효세율 택사노미 검토 (분반기) | N23: ='Checklist_2-6'!$B$11 -> 0
B24: 3 | C24: 축-멤버 정합성 검토 | D24: • 표준 축-멤버 구조 정합성 | N24: ='Checklist_3-1'!B11 -> 0
D25: • 공시금액의 사용 적정성 | N25: ='Checklist_3-2'!B11 -> 0
B26: 4 | C26: 전용요소 사용 검토 | D26: • 현금흐름 관련 표 내에서 다른 요소 사용 | N26: ='Checklist_4-1'!B11 -> 0
D27: • 현금흐름 관련 표의 전용요소가 다른 표에서 사용 | N27: ='Checklist_4-2'!B11 -> 0
D28: • 판매관리비 관련 표내에서 다른 요소 사용 | N28: ='Checklist_4-3'!B11 -> 0
D29: • 판매비와관리비 관련 표의 전용요소가 다른 표에서 사용 | N29: ='Checklist_4-4'!B11 -> 0
D30: • 특수관계자 관련 표 내에서 다른 요소 사용 | N30: ='Checklist_4-5'!B11 -> 0
D31: • 특수관계자 관련 표의 전용요소가 다른 표에서 사용 | N31: ='Checklist_4-6'!B11 -> 0
B32: 5 | C32: 속성/데이터타입 검토 | D32: • Percent 소숫점 자리수 검토 | N32: ='Checklist_5-1'!B11 -> 0
D33: • 보유하는 주식수 속성 검토 | N33: ='Checklist_5-2'!B11 -> 0
D34: • 이연법인세부채(자산)은 텍사노미 및 부호 검토 | N34: ='Checklist_5-3'!B11 -> 0
D35: • 기본주당이익/희석주당이익 속성 검토 | N35: ='Checklist_5-4'!B11 -> 0
D36: • 기초/기말 영문명 검토 | N36: ='Checklist_5-5'!B11 -> 0
D37: • 단위미사용 검토 | N37: ='Checklist_5-6'!B11 -> 0
B38: 6 | C38: 확장 검토 | D38: • 축 확장 검토 | N38: ='Checklist_6-1'!B11 -> 0
D39: • 멤버 합계열 적절성 검토 | N39: ='Checklist_6-2'!B11 -> 0
D40: • Duration / Instant 속성 검토 | N40: ='Checklist_6-3'!B11 -> 0
D41: • negated 검토 | N41: ='Checklist_7-1'!B11 -> 0
B46: 7 | C46: 기타

Sheet Checklist_1-1
B2: 총액계정 사용 검토
B3: ※ XBRL Checklist 결과는 참고 목적으로 제공드리는 내역으로, 텍사노미 구조와 관련된 리뷰는 CoE 업무 Scope에 포함되지 않습니다.
L4: Reference - 금감원 가이드 86page
B11: 0 | C11: 개 항목이 추출되었습니다.
B13: Role Definition | C13: TABLE NAME | D13: Prefix | E13: Name | F13: Label(KO) | G13: Label(EN) | H13: Label Role | I13: DataType | J13: Period

Sheet Checklist_1-2
B2: 초과적립액(과소적립액) 텍사노미 사용 검토
B3: ※ XBRL Checklist 결과는 참고 목적으로 제공드리는 내역으로, 텍사노미 구조와 관련된 리뷰는 CoE 업무 Scope에 포함되지 않습니다.
L4: Reference - 금감원 가이드 228page
B11: 0 | C11: 개 항목이 추출되었습니다.
B13: Role Definition | C13: TABLE NAME | D13: Prefix | E13: Name | F13: Label(KO) | G13: Label(EN) | H13: Label Role | I13: DataType | J13: Period

Sheet Checklist_1-3
B2: 재고자산 세부내역 표 검토
B3: ※ XBRL Checklist 결과는 참고 목적으로 제공드리는 내역으로, 텍사노미 구조와 관련된 리뷰는 CoE 업무 Scope에 포함되지 않습니다.
B11: 0 | C11: 개 항목이 추출되었습니다.
B13: Role Definition | C13: TABLE NAME | D13: Prefix | E13: Name | F13: Label(KO) | G13: Label(EN) | H13: Label Role | I13: DataType | J13: Period

Sheet Checklist_1-4
B2: 유동/비유동 축 검토
B3: ※ XBRL Checklist 결과는 참고 목적으로 제공드리는 내역으로, 텍사노미 구조와 관련된 리뷰는 CoE 업무 Scope에 포함되지 않습니다.
B11: 0 | C11: 개 항목이 추출되었습니다.
B13: Role Definition | C13: TABLE NAME | D13: Prefix | E13: Name | F13: Label(KO) | G13: Label(EN) | H13: Label Role | I13: DataType | J13: Period

Sheet Checklist_2-1
B2: 만료 택사노미 검토 - 대손충당금
B3: ※ XBRL Checklist 결과는 참고 목적으로 제공드리는 내역으로, 텍사노미 구조와 관련된 리뷰는 CoE 업무 Scope에 포함되지 않습니다.
B11: 0 | C11: 개 항목이 추출되었습니다.
B13: Role Definition | C13: TABLE NAME | D13: Prefix | E13: Name | F13: Label(KO) | G13: Label(EN) | H13: Label Role | I13: DataType | J13: Period

Sheet Checklist_2-2
B2: 만료 택사노미 검토 - 손상차손 축
B3: ※ XBRL Checklist 결과는 참고 목적으로 제공드리는 내역으로, 텍사노미 구조와 관련된 리뷰는 CoE 업무 Scope에 포함되지 않습니다.
B11: 0 | C11: 개 항목이 추출되었습니다.
B13: Role Definition | C13: TABLE NAME | D13: Prefix | E13: Name | F13: Label(KO) | G13: Label(EN) | H13: Label Role | I13: DataType | J13: Period

Sheet Checklist_2-3
B2: 택사노미 검토 - 대출약정금액
B3: ※ XBRL Checklist 결과는 참고 목적으로 제공드리는 내역으로, 텍사노미 구조와 관련된 리뷰는 CoE 업무 Scope에 포함되지 않습니다.
B11: 0 | C11: 개 항목이 추출되었습니다.
B13: Role Definition | C13: TABLE NAME | D13: Prefix | E13: Name | F13: Label(KO) | G13: Label(EN) | H13: Label Role | I13: DataType | J13: Period

Sheet Checklist_2-4
B2: 택사노미 검토 - 미착품
B3: ※ XBRL Checklist 결과는 참고 목적으로 제공드리는 내역으로, 텍사노미 구조와 관련된 리뷰는 CoE 업무 Scope에 포함되지 않습니다.
B11: 0 | C11: 개 항목이 추출되었습니다.
B13: Role Definition | C13: TABLE NAME | D13: Prefix | E13: Name | F13: Label(KO) | G13: Label(EN) | H13: Label Role | I13: DataType | J13: Period

Sheet Checklist_2-5
B2: 택사노미 검토 - 배당금
B3: ※ XBRL Checklist 결과는 참고 목적으로 제공드리는 내역으로, 텍사노미 구조와 관련된 리뷰는 CoE 업무 Scope에 포함되지 않습니다.
B11: 7 | C11: 개 항목이 추출되었습니다.
B13: Role Definition | C13: TABLE NAME | D13: Prefix | E13: Name | F13: Label(KO) | G13: Label(EN) | H13: Label Role | I13: DataType | J13: Period
B14: [D610000] 자본변동표 - 연결 | Statement of changes in equity - Consolidated financial statements | C14: 자본변동표 [표] | D14: ifrs-full | E14: DividendsPaid | F14: 소유주에 대한 배분으로 인식된 배당금 | G14: Dividends recognised as distributions to owners | H14: negatedLabel | I14: xbrli:monetaryItemType | J14: DURATION
B15: [D861310] 24. 배당금 | 24. Dividends | C15: 배당금에 대한 공시 [표] | D15: dart | E15: DividendsPayableOrdinarySharesPerShare | F15: 보통주에 지급될 주당배당금(단위:원) | G15: Dividends payable, ordinary shares per share(Unit:Won) | H15: terseLabel | I15: num:perShareItemType | J15: DURATION
B16: [D861310] 24. 배당금 | 24. Dividends | C16: 배당금에 대한 공시 [표] | D16: ifrs-full | E16: DividendsProposedOrDeclaredBeforeFinancialStatementsAuthorisedForIssueButNotRecognisedAsDistributionToOwners | F16: 재무제표 발행승인일 전에 제안 또는 선언되었으나 당해 기간 동안에 소유주에 대한 분배금으로 인식되지 아니한 배당금 | G16: Dividends proposed or declared before financial statements authorised for issue but not recognised as distribution to owners | I16: xbrli:monetaryItemType | J16: DURATION
B17: [D610005] 자본변동표 - 별도 | Statement of changes in equity - Separate financial statements | C17: 자본변동표 [표] | D17: ifrs-full | E17: DividendsPaid | F17: 소유주에 대한 배분으로 인식된 배당금 | G17: Dividends recognised as distributions to owners | H17: negatedLabel | I17: xbrli:monetaryItemType | J17: DURATION
B18: [D861205] 21. 자본 | 21. Equity | C18: 이익잉여금 처분계산서 | D18: ifrs-full | E18: DividendsProposedOrDeclaredBeforeFinancialStatementsAuthorisedForIssueButNotRecognisedAsDistributionToOwners | F18: 재무제표 발행승인일 전에 제안 또는 선언되었으나 당해 기간 동안에 소유주에 대한 분배금으로 인식되지 아니한 배당금 | G18: Dividends proposed or declared before financial statements authorised for issue but not recognised as distribution to owners | I18: xbrli:monetaryItemType | J18: DURATION
B19: [D861315] 23. 배당금 | 23. Dividends | C19: 배당금에 대한 공시 [표] | D19: dart | E19: DividendsPayableOrdinarySharesPerShare | F19: 보통주에 지급될 주당배당금(단위:원) | G19: Dividends payable, ordinary shares per share(Unit:Won) | H19: terseLabel | I19: num:perShareItemType | J19: DURATION
B20: [D861315] 23. 배당금 | 23. Dividends | C20: 배당금에 대한 공시 [표] | D20: ifrs-full | E20: DividendsProposedOrDeclaredBeforeFinancialStatementsAuthorisedForIssueButNotRecognisedAsDistributionToOwners | F20: 재무제표 발행승인일 전에 제안 또는 선언되었으나 당해 기간 동안에 소유주에 대한 분배금으로 인식되지 아니한 배당금 | G20: Dividends proposed or declared before financial statements authorised for issue but not recognised as distribution to owners | I20: xbrli:monetaryItemType | J20: DURATION

Sheet Checklist_2-6
B2: 택사노미 검토 - 평균유효세율
B3: ※ XBRL Checklist 결과는 참고 목적으로 제공드리는 내역으로, 텍사노미 구조와 관련된 리뷰는 CoE 업무 Scope에 포함되지 않습니다.
B11: 0 | C11: 개 항목이 추출되었습니다.
B13: Role Definition | C13: TABLE NAME | D13: Prefix | E13: Name | F13: Label(KO) | G13: Label(EN) | H13: Label Role | I13: DataType | J13: Period

Sheet Checklist_3-1
B2: 축-멤버 구조 정합성 검토
B3: ※ XBRL Checklist 결과는 참고 목적으로 제공드리는 내역으로, 텍사노미 구조와 관련된 리뷰는 CoE 업무 Scope에 포함되지 않습니다.
B11: 61 | C11: 개 항목이 추출되었습니다.
B13: Role Definition | C13: TABLE NAME | D13: Prefix | E13: Name | F13: Label(KO) | G13: Label(EN) | H13: Label Role | I13: DataType | J13: Period
B14: [D823000] 5. 금융상품 공정가치 | 5. Fair value of financial instruments | C14: 공정가치로 측정하는 금융상품 중 수준3으로 분류된 항목의 변동내역 | D14: ifrs-full | E14: FinancialAssetsAtFairValueThroughProfitOrLossCategoryMember | F14: 당기손익인식금융자산 [구성요소] | G14: Financial assets at fair value through profit or loss, category [member] | I14: nonnum:domainItemType | J14: DURATION
B15: [D823000] 5. 금융상품 공정가치 | 5. Fair value of financial instruments | C15: 공정가치로 측정하는 금융상품 중 수준3으로 분류된 항목의 변동내역 | D15: ifrs-full | E15: FinancialAssetsAtFairValueThroughOtherComprehensiveIncomeCategoryMember | F15: 공정가치평가를 기타포괄손익으로 인식하는 금융자산 [구성요소] | G15: Financial assets at fair value through other comprehensive income, category [member] | I15: nonnum:domainItemType | J15: DURATION
B16: [D823000] 5. 금융상품 공정가치 | 5. Fair value of financial instruments | C16: 자산의 공정가치측정에 사용된 관측가능하지 않은 투입변수에 대한 공시 [표] | D16: ifrs-full | E16: FinancialAssetsAtFairValueThroughProfitOrLossCategoryMember | F16: 당기손익인식금융자산 [구성요소] | G16: Financial assets at fair value through profit or loss, category [member] | I16: nonnum:domainItemType | J16: DURATION
B17: [D823000] 5. 금융상품 공정가치 | 5. Fair value of financial instruments | C17: 자산의 공정가치측정에 사용된 관측가능하지 않은 투입변수에 대한 공시 [표] | D17: ifrs-full | E17: FinancialAssetsAtFairValueThroughOtherComprehensiveIncomeCategoryMember | F17: 공정가치평가를 기타포괄손익으로 인식하는 금융자산 [구성요소] | G17: Financial assets at fair value through other comprehensive income, category [member] | I17: nonnum:domainItemType | J17: DURATION
B18: [D822420] 8. 매출채권 및 기타채권 | 8. Trade and other receivables | C18: 연체되거나 손상된 매출채권 및 기타채권에 대한 공시 [표] | D18: ifrs-full | E18: LaterThanThreeMonthsAndNotLaterThanSixMonthsMember | F18: 3개월 초과 6개월 이내 [구성요소] | G18: Later than three months and not later than six months [member] | I18: nonnum:domainItemType | J18: DURATION
B19: [D822420] 8. 매출채권 및 기타채권 | 8. Trade and other receivables | C19: 연체되거나 손상된 매출채권의 장부금액에 대한 공시 | D19: ifrs-full | E19: LaterThanThreeMonthsAndNotLaterThanSixMonthsMember | F19: 3개월 초과 6개월 이내 [구성요소] | G19: Later than three months and not later than six months [member] | I19: nonnum:domainItemType | J19: DURATION
B20: [D835110] 29. 법인세 | 29. Income taxes | C20: 일시적차이, 미사용 세무상 결손금과 미사용 세액공제에 대한 공시 [표] | D20: ifrs-full | E20: AccumulatedImpairmentMember | F20: 손상차손누계액 [구성요소] | G20: Accumulated impairment [member] | I20: nonnum:domainItemType | J20: DURATION
B21: [D835110] 29. 법인세 | 29. Income taxes | C21: 일시적차이, 미사용 세무상 결손금과 미사용 세액공제에 대한 공시 [표] | D21: dart | E21: AccruedIncomeMember | F21: 미수수익 [구성요소] | G21: Accrued income [member] | I21: nonnum:domainItemType | J21: DURATION
B22: [D835110] 29. 법인세 | 29. Income taxes | C22: 일시적차이, 미사용 세무상 결손금과 미사용 세액공제에 대한 공시 [표] | D22: ifrs-full | E22: FinancialAssetsAtFairValueThroughProfitOrLossCategoryMember | F22: 당기손익인식금융자산 [구성요소] | G22: Financial assets at fair value through profit or loss, category [member] | I22: nonnum:domainItemType | J22: DURATION
B23: [D835110] 29. 법인세 | 29. Income taxes | C23: 일시적차이, 미사용 세무상 결손금과 미사용 세액공제에 대한 공시 [표] | D23: ifrs-full | E23: PresentValueOfDefinedBenefitObligationMember | F23: 퇴직급여채무 [구성요소] | G23: Defined benefit obligations [member] | H23: terseLabel | I23: nonnum:domainItemType | J23: DURATION
B24: [D835110] 29. 법인세 | 29. Income taxes | C24: 일시적차이, 미사용 세무상 결손금과 미사용 세액공제에 대한 공시 [표] | D24: ifrs-full | E24: PlanAssetsMember | F24: 사외적립자산 [구성요소] | G24: Plan assets [member] | I24: nonnum:domainItemType | J24: DURATION
B25: [D835110] 29. 법인세 | 29. Income taxes | C25: 일시적차이, 미사용 세무상 결손금과 미사용 세액공제에 대한 공시 [표] | D25: dart | E25: AllowanceForInventoryValuationMember | F25: 재고자산 평가충당금 [구성요소] | G25: Allowance For Inventory Valuation [Member] | I25: nonnum:domainItemType | J25: DURATION
B26: [D835110] 29. 법인세 | 29. Income taxes | C26: 일시적차이, 미사용 세무상 결손금과 미사용 세액공제에 대한 공시 [표] | D26: ifrs-full | E26: FinancialAssetsAtFairValueThroughOtherComprehensiveIncomeCategoryMember | F26: 공정가치평가를 기타포괄손익으로 인식하는 금융자산 [구성요소] | G26: Financial assets at fair value through other comprehensive income, category [member] | I26: nonnum:domainItemType | J26: DURATION
B27: [D835110] 29. 법인세 | 29. Income taxes | C27: 일시적차이, 미사용 세무상 결손금과 미사용 세액공제에 대한 공시 [표] | D27: ifrs-full | E27: WarrantyProvisionMember | F27: 판매보증충당금 [구성요소] | G27: Provision for sales warranties [member] | H27: terseLabel | I27: nonnum:domainItemType | J27: DURATION
B28: [D835110] 29. 법인세 | 29. Income taxes | C28: 일시적차이, 미사용 세무상 결손금과 미사용 세액공제에 대한 공시 [표] | D28: ifrs-full | E28: InvestmentsAccountedForUsingEquityMethodMember | F28: 지분법적용 투자지분 [구성요소] | G28: Investments accounted for using equity method [member] | I28: nonnum:domainItemType | J28: DURATION
B29: [D835110] 29. 법인세 | 29. Income taxes | C29: 일시적차이, 미사용 세무상 결손금과 미사용 세액공제에 대한 공시 [표] | D29: ifrs-full | E29: VehiclesMember | F29: 차량운반구 [구성요소] | G29: Vehicles [member] | I29: nonnum:domainItemType | J29: DURATION
B30: [D835110] 29. 법인세 | 29. Income taxes | C30: 일시적차이, 미사용 세무상 결손금과 미사용 세액공제에 대한 공시 [표] | D30: ifrs-full | E30: ProvisionForCreditCommitmentsMember | F30: 채무보증충당부채 [구성요소] | G30: Provision for financial guarantee obligations [member] | H30: terseLabel | I30: nonnum:domainItemType | J30: DURATION
B31: [D835110] 29. 법인세 | 29. Income taxes | C31: 일시적차이, 미사용 세무상 결손금과 미사용 세액공제에 대한 공시 [표] | D31: ifrs-full | E31: MiscellaneousOtherProvisionsMember | F31: 복구충당부채 [구성요소] | G31: Provision for asset retirement obligations [member] | H31: terseLabel | I31: nonnum:domainItemType | J31: DURATION
B32: [D835110] 29. 법인세 | 29. Income taxes | C32: 일시적차이, 미사용 세무상 결손금과 미사용 세액공제에 대한 공시 [표] | D32: ifrs-full | E32: LeaseReceivablesMember | F32: 리스채권 [구성요소] | G32: Lease receivables [member] | I32: nonnum:domainItemType | J32: DURATION
B33: [D835110] 29. 법인세 | 29. Income taxes | C33: 일시적차이, 미사용 세무상 결손금과 미사용 세액공제에 대한 공시 [표] | D33: ifrs-full | E33: LeaseLiabilitiesMember | F33: 리스 부채 [구성요소] | G33: Lease liabilities [member] | I33: nonnum:domainItemType | J33: DURATION
B34: [D835110] 29. 법인세 | 29. Income taxes | C34: 일시적차이, 미사용 세무상 결손금과 미사용 세액공제에 대한 공시 [표] | D34: dart | E34: OtherPayablesMember | F34: 기타 미지급금 [구성요소] | G34: Other payables [member] | I34: nonnum:domainItemType | J34: DURATION
B35: [D835110] 29. 법인세 | 29. Income taxes | C35: 일시적차이, 미사용 세무상 결손금과 미사용 세액공제에 대한 공시 [표] | D35: ifrs-full | E35: AccumulatedDepreciationAndAmortisationMember | F35: 감가상각누계액 및 상각누계액 [구성요소] | G35: Accumulated depreciation and amortisation [member] | I35: nonnum:domainItemType | J35: DURATION
B36: [D835110] 29. 법인세 | 29. Income taxes | C36: 일시적차이, 미사용 세무상 결손금과 미사용 세액공제에 대한 공시 [표] | D36: ifrs-full | E36: CapitalisedDevelopmentExpenditureMember | F36: 자본화된 개발비 지출액 [구성요소] | G36: Capitalised development expenditure [member] | I36: nonnum:domainItemType | J36: DURATION
B37: [D835110] 29. 법인세 | 29. Income taxes | C37: 일시적차이, 미사용 세무상 결손금과 미사용 세액공제에 대한 공시 [표] | D37: dart | E37: StructureMember | F37: 구축물 [구성요소] | G37: Structure [member] | I37: nonnum:domainItemType | J37: DURATION
B38: [D835110] 29. 법인세 | 29. Income taxes | C38: 일시적차이, 미사용 세무상 결손금과 미사용 세액공제에 대한 공시 [표] | D38: dart | E38: RightForFacilityUseMember | F38: 회원권 [구성요소] | G38: Right for facility use [member] | I38: nonnum:domainItemType | J38: DURATION
B39: [D835110] 29. 법인세 | 29. Income taxes | C39: 일시적차이, 미사용 세무상 결손금과 미사용 세액공제에 대한 공시 [표] | D39: ifrs-full | E39: ReserveOfSharebasedPaymentsMember | F39: 주식기준보상 적립금 [구성요소] | G39: Reserve of share-based payments [member] | I39: nonnum:domainItemType | J39: DURATION
B40: [D827580] 33. 약정사항 및 우발사항 | 33. Commitments and contingencies | C40: 담보로 제공된 자산에 대한 공시 | D40: ifrs-full | E40: TradingSecuritiesMember | F40: 단기매매 증권 [구성요소] | G40: Trading securities [member] | I40: nonnum:domainItemType | J40: DURATION
B41: [D822380] 36. 위험관리 | 36. Risk management | C41: 외화금융자산의 통화별 내역 [표] | D41: dart | E41: ReceivablesMember | F41: 미수금 [구성요소] | G41: Receivables [member] | I41: nonnum:domainItemType | J41: DURATION
B42: [D822380] 36. 위험관리 | 36. Risk management | C42: 외화금융부채의 통화별 내역 [표] | D42: dart | E42: OtherPayablesMember | F42: 기타 미지급금 [구성요소] | G42: Other payables [member] | I42: nonnum:domainItemType | J42: DURATION
B43: [D822380] 36. 위험관리 | 36. Risk management | C43: 신용위험 익스포저에 대한 공시 [표] | D43: ifrs-full | E43: TradingSecuritiesMember | F43: 단기매매 증권 [구성요소] | G43: Trading securities [member] | I43: nonnum:domainItemType | J43: DURATION
... B52: [D835115] 28. 법인세 | 28. Income taxes | C52: 일시적차이, 미사용 세무상 결손금과 미사용 세액공제에 대한 공시 [표] | D52: dart | E52: AccruedIncomeMember | F52: 미수수익 [구성요소] | G52: Accrued income [member] | I52: nonnum:domainItemType | J52: DURATION
B53: [D835115] 28. 법인세 | 28. Income taxes | C53: 일시적차이, 미사용 세무상 결손금과 미사용 세액공제에 대한 공시 [표] | D53: ifrs-full | E53: PresentValueOfDefinedBenefitObligationMember | F53: 퇴직급여채무 [구성요소] | G53: Defined benefit obligations [member] | H53: terseLabel | I53: nonnum:domainItemType | J53: DURATION
B54: [D835115] 28. 법인세 | 28. Income taxes | C54: 일시적차이, 미사용 세무상 결손금과 미사용 세액공제에 대한 공시 [표] | D54: ifrs-full | E54: PlanAssetsMember | F54: 사외적립자산 [구성요소] | G54: Plan assets [member] | I54: nonnum:domainItemType | J54: DURATION
B55: [D835115] 28. 법인세 | 28. Income taxes | C55: 일시적차이, 미사용 세무상 결손금과 미사용 세액공제에 대한 공시 [표] | D55: dart | E55: AllowanceForInventoryValuationMember | F55: 제품평가충당금 [구성요소] | G55: Allowance For finished goods Valuation [Member] | H55: terseLabel | I55: nonnum:domainItemType | J55: DURATION
B56: [D835115] 28. 법인세 | 28. Income taxes | C56: 일시적차이, 미사용 세무상 결손금과 미사용 세액공제에 대한 공시 [표] | D56: ifrs-full | E56: FinancialAssetsAtFairValueThroughOtherComprehensiveIncomeCategoryMember | F56: 공정가치평가를 기타포괄손익으로 인식하는 금융자산 [구성요소] | G56: Financial assets at fair value through other comprehensive income, category [member] | I56: nonnum:domainItemType | J56: DURATION
B57: [D835115] 28. 법인세 | 28. Income taxes | C57: 일시적차이, 미사용 세무상 결손금과 미사용 세액공제에 대한 공시 [표] | D57: ifrs-full | E57: WarrantyProvisionMember | F57: 판매보증충당금 [구성요소] | G57: Provision for sales warranties [member] | H57: terseLabel | I57: nonnum:domainItemType | J57: DURATION
B58: [D835115] 28. 법인세 | 28. Income taxes | C58: 일시적차이, 미사용 세무상 결손금과 미사용 세액공제에 대한 공시 [표] | D58: ifrs-full | E58: InvestmentsAccountedForUsingEquityMethodMember | F58: 지분법적용 투자지분 [구성요소] | G58: Investments accounted for using equity method [member] | I58: nonnum:domainItemType | J58: DURATION
B59: [D835115] 28. 법인세 | 28. Income taxes | C59: 일시적차이, 미사용 세무상 결손금과 미사용 세액공제에 대한 공시 [표] | D59: ifrs-full | E59: VehiclesMember | F59: 차량운반구 [구성요소] | G59: Vehicles [member] | I59: nonnum:domainItemType | J59: DURATION
B60: [D835115] 28. 법인세 | 28. Income taxes | C60: 일시적차이, 미사용 세무상 결손금과 미사용 세액공제에 대한 공시 [표] | D60: ifrs-full | E60: ProvisionForCreditCommitmentsMember | F60: 채무보증충당부채 [구성요소] | G60: Provision for financial guarantee obligations [member] | H60: terseLabel | I60: nonnum:domainItemType | J60: DURATION
B61: [D835115] 28. 법인세 | 28. Income taxes | C61: 일시적차이, 미사용 세무상 결손금과 미사용 세액공제에 대한 공시 [표] | D61: ifrs-full | E61: MiscellaneousOtherProvisionsMember | F61: 복구충당부채 [구성요소] | G61: Provision for asset retirement obligations [member] | H61: terseLabel | I61: nonnum:domainItemType | J61: DURATION
B62: [D835115] 28. 법인세 | 28. Income taxes | C62: 일시적차이, 미사용 세무상 결손금과 미사용 세액공제에 대한 공시 [표] | D62: ifrs-full | E62: LeaseReceivablesMember | F62: 리스채권 [구성요소] | G62: Lease receivables [member] | I62: nonnum:domainItemType | J62: DURATION
B63: [D835115] 28. 법인세 | 28. Income taxes | C63: 일시적차이, 미사용 세무상 결손금과 미사용 세액공제에 대한 공시 [표] | D63: ifrs-full | E63: LeaseLiabilitiesMember | F63: 리스 부채 [구성요소] | G63: Lease liabilities [member] | I63: nonnum:domainItemType | J63: DURATION
B64: [D835115] 28. 법인세 | 28. Income taxes | C64: 일시적차이, 미사용 세무상 결손금과 미사용 세액공제에 대한 공시 [표] | D64: ifrs-full | E64: CapitalisedDevelopmentExpenditureMember | F64: 자본화된 개발비 지출액 [구성요소] | G64: Capitalised development expenditure [member] | I64: nonnum:domainItemType | J64: DURATION
B65: [D835115] 28. 법인세 | 28. Income taxes | C65: 일시적차이, 미사용 세무상 결손금과 미사용 세액공제에 대한 공시 [표] | D65: dart | E65: StructureMember | F65: 구축물 [구성요소] | G65: Structure [member] | I65: nonnum:domainItemType | J65: DURATION
B66: [D835115] 28. 법인세 | 28. Income taxes | C66: 일시적차이, 미사용 세무상 결손금과 미사용 세액공제에 대한 공시 [표] | D66: dart | E66: RightForFacilityUseMember | F66: 회원권 [구성요소] | G66: Right for facility use [member] | I66: nonnum:domainItemType | J66: DURATION
B67: [D835115] 28. 법인세 | 28. Income taxes | C67: 일시적차이, 미사용 세무상 결손금과 미사용 세액공제에 대한 공시 [표] | D67: ifrs-full | E67: ReserveOfSharebasedPaymentsMember | F67: 주식기준보상 적립금 [구성요소] | G67: Reserve of share-based payments [member] | I67: nonnum:domainItemType | J67: DURATION
B68: [D827585] 32. 약정사항 및 우발사항 | 32. Commitments and contingencies | C68: 담보로 제공된 자산에 대한 공시 | D68: ifrs-full | E68: TradingSecuritiesMember | F68: 단기매매 증권 [구성요소] | G68: Trading securities [member] | I68: nonnum:domainItemType | J68: DURATION
B69: [D827585] 32. 약정사항 및 우발사항 | 32. Commitments and contingencies | C69: 차입금 관련 담보제공자산의 공시 | D69: ifrs-full | E69: TradingSecuritiesMember | F69: 단기매매 증권 [구성요소] | G69: Trading securities [member] | I69: nonnum:domainItemType | J69: DURATION
B70: [D822385] 35. 위험관리 | 35. Risk management | C70: 외화금융자산의 통화별 내역 [표] | D70: dart | E70: ReceivablesMember | F70: 미수금 [구성요소] | G70: Receivables [member] | I70: nonnum:domainItemType | J70: DURATION
B71: [D822385] 35. 위험관리 | 35. Risk management | C71: 외화금융자산의 통화별 내역 [표] | D71: dart | E71: LoanMember | F71: 대여금 [구성요소] | G71: Loans [member] | I71: nonnum:domainItemType | J71: DURATION
B72: [D822385] 35. 위험관리 | 35. Risk management | C72: 외화금융부채의 통화별 내역 [표] | D72: dart | E72: OtherPayablesMember | F72: 기타 미지급금 [구성요소] | G72: Other payables [member] | I72: nonnum:domainItemType | J72: DURATION
B73: [D822385] 35. 위험관리 | 35. Risk management | C73: 신용위험 익스포저에 대한 공시 [표] | D73: ifrs-full | E73: TradingSecuritiesMember | F73: 단기매매 증권 [구성요소] | G73: Trading securities [member] | I73: nonnum:domainItemType | J73: DURATION
B74: [D822385] 35. 위험관리 | 35. Risk management | C74: 신용위험 익스포저에 대한 공시 [표] | D74: dart | E74: OtherFinancialAssetsMember | F74: 기타금융자산 [구성요소] | G74: Other financial assets [member] | I74: nonnum:domainItemType | J74: DURATION

Sheet Checklist_3-2
B2: 공시금액의 사용 적정성 검토
B3: ※ XBRL Checklist 결과는 참고 목적으로 제공드리는 내역으로, 텍사노미 구조와 관련된 리뷰는 CoE 업무 Scope에 포함되지 않습니다.
L4: Reference - 금감원 가이드 137page
B11: 6 | C11: 개 항목이 추출되었습니다.
B13: Role Definition | C13: TABLE NAME | D13: Prefix | E13: Name | F13: Label(KO) | G13: Label(EN) | H13: Label Role | I13: DataType | J13: Period
B14: [D822100] 11. 유형자산 | 11. Property, plant and equipment | C14: 유형자산에 대한 세부 정보 공시 | D14: dart | E14: ReportedAmountMember | F14: 공시금액 [구성요소] | G14: Disclosed Amount [member] | I14: nonnum:domainItemType | J14: DURATION
B15: [D825100] 12. 투자부동산 | 12. Investment property | C15: 투자부동산에 대한 세부 정보 공시 [표] | D15: dart | E15: ReportedAmountMember | F15: 공시금액 [구성요소] | G15: Disclosed Amount [member] | I15: nonnum:domainItemType | J15: DURATION
B16: [D823180] 15. 무형자산 | 15. Intangible assets | C16: 무형자산에 대한 세부 정보 공시 | D16: dart | E16: ReportedAmountMember | F16: 공시금액 [구성요소] | G16: Disclosed Amount [member] | I16: nonnum:domainItemType | J16: DURATION
B17: [D822105] 11. 유형자산 | 11. Property, plant and equipment | C17: 유형자산에 대한 세부 정보 공시 | D17: dart | E17: ReportedAmountMember | F17: 공시금액 [구성요소] | G17: Disclosed Amount [member] | I17: nonnum:domainItemType | J17: DURATION
B18: [D825105] 12. 투자부동산 | 12. Investment property | C18: 투자부동산에 대한 세부 정보 공시 [표] | D18: dart | E18: ReportedAmountMember | F18: 공시금액 [구성요소] | G18: Disclosed Amount [member] | I18: nonnum:domainItemType | J18: DURATION
B19: [D823185] 15. 무형자산 | 15. Intangible assets | C19: 무형자산에 대한 세부 정보 공시 | D19: dart | E19: ReportedAmountMember | F19: 공시금액 [구성요소] | G19: Disclosed Amount [member] | I19: nonnum:domainItemType | J19: DURATION

Sheet Checklist_4-1
B2: 현금흐름표 관련 전용요소 검토 (1)
B3: ※ XBRL Checklist 결과는 참고 목적으로 제공드리는 내역으로, 텍사노미 구조와 관련된 리뷰는 CoE 업무 Scope에 포함되지 않습니다.
L4: Reference - 금감원 가이드 158page
B11: 0 | C11: 개 항목이 추출되었습니다.
B13: Role Definition | C13: TABLE NAME | D13: Prefix | E13: Name | F13: Label(KO) | G13: Label(EN) | H13: Label Role | I13: DataType | J13: Period

Sheet Checklist_4-2
B2: 현금흐름표 관련 전용요소 검토 (2)
B3: ※ XBRL Checklist 결과는 참고 목적으로 제공드리는 내역으로, 텍사노미 구조와 관련된 리뷰는 CoE 업무 Scope에 포함되지 않습니다.
B11: 0 | C11: 개 항목이 추출되었습니다.
B13: Role Definition | C13: TABLE NAME | D13: Prefix | E13: Name | F13: Label(KO) | G13: Label(EN) | H13: Label Role | I13: DataType | J13: Period

Sheet Checklist_4-3
B2: 판매비와관리비 관련 전용요소 검토 (1)
B3: ※ XBRL Checklist 결과는 참고 목적으로 제공드리는 내역으로, 텍사노미 구조와 관련된 리뷰는 CoE 업무 Scope에 포함되지 않습니다.
L4: Reference - 금감원 가이드 157page
B11: 0 | C11: 개 항목이 추출되었습니다.
B13: Role Definition | C13: TABLE NAME | D13: Prefix | E13: Name | F13: Label(KO) | G13: Label(EN) | H13: Label Role | I13: DataType | J13: Period

Sheet Checklist_4-4
B2: 판매비와관리비 관련 전용요소 검토 (2)
B3: ※ XBRL Checklist 결과는 참고 목적으로 제공드리는 내역으로, 텍사노미 구조와 관련된 리뷰는 CoE 업무 Scope에 포함되지 않습니다.
B11: 0 | C11: 개 항목이 추출되었습니다.
B13: Role Definition | C13: TABLE NAME | D13: Prefix | E13: Name | F13: Label(KO) | G13: Label(EN) | H13: Label Role | I13: DataType | J13: Period

Sheet Checklist_4-5
B2: 특수관계자 관련 전용요소 검토 (1)
B3: ※ XBRL Checklist 결과는 참고 목적으로 제공드리는 내역으로, 텍사노미 구조와 관련된 리뷰는 CoE 업무 Scope에 포함되지 않습니다. | L3: Reference - 금감원 가이드 158page
B11: 10 | C11: 개 항목이 추출되었습니다.
B13: Role Definition | C13: TABLE NAME | D13: Prefix | E13: Name | F13: Label(KO) | G13: Label(EN) | H13: Label Role | I13: DataType | J13: Period
B14: [D818000] 32. 특수관계자 거래 | 32. Related party transactions | C14: 특수관계자 현황의 공시 | D14: ifrs-full | E14: CountryOfIncorporationOrResidenceOfAssociate | F14: 관계기업의 설립지 국가 | G14: Country of incorporation of associate | I14: xbrli:stringItemType | J14: DURATION
B15: [D818000] 32. 특수관계자 거래 | 32. Related party transactions | C15: 특수관계자 현황의 공시 | D15: ifrs-full | E15: ProportionOfOwnershipInterestInAssociate | F15: 관계기업에 대한 소유지분율 | G15: Proportion of ownership interest in associate | I15: num:percentItemType | J15: DURATION
B16: [D818005] 31. 특수관계자 거래 | 31. Related party transactions | C16: 특수관계자 현황의 공시 | D16: ifrs-full | E16: CountryOfIncorporationOrResidenceOfSubsidiary | F16: 종속기업의 설립지 국가 | G16: Country of incorporation of subsidiary | I16: xbrli:stringItemType | J16: DURATION
B17: [D818005] 31. 특수관계자 거래 | 31. Related party transactions | C17: 특수관계자 현황의 공시 | D17: ifrs-full | E17: ProportionOfOwnershipInterestInSubsidiary | F17: 종속기업에 대한 소유지분율 | G17: Proportion of ownership interest in subsidiary | I17: num:percentItemType | J17: DURATION
B18: [D818005] 31. 특수관계자 거래 | 31. Related party transactions | C18: 특수관계자 현황의 공시 | D18: ifrs-full | E18: CountryOfIncorporationOrResidenceOfAssociate | F18: 관계기업의 설립지 국가 | G18: Country of incorporation of associate | I18: xbrli:stringItemType | J18: DURATION
B19: [D818005] 31. 특수관계자 거래 | 31. Related party transactions | C19: 특수관계자 현황의 공시 | D19: ifrs-full | E19: ProportionOfOwnershipInterestInAssociate | F19: 관계기업에 대한 소유지분율 | G19: Proportion of ownership interest in associate | I19: num:percentItemType | J19: DURATION
B20: [D818005] 31. 특수관계자 거래 | 31. Related party transactions | C20: 특수관계자 지급보증에 대한 공시 | D20: dart | E20: GuaranteeLimitAmount | F20: 보증한도 | G20: Guarantee limit amount | I20: xbrli:monetaryItemType | J20: INSTANT
B21: [D818005] 31. 특수관계자 거래 | 31. Related party transactions | C21: 특수관계자 지급보증에 대한 공시 | D21: dart | E21: TypeOfGuarantee | F21: 보증종류 | G21: Type of guarantee | I21: xbrli:stringItemType | J21: DURATION
B22: [D818005] 31. 특수관계자 거래 | 31. Related party transactions | C22: 특수관계자 지급보증에 대한 공시 | D22: dart | E22: GuaranteeProvider | F22: 보증처 | G22: Guarantee provider | I22: xbrli:stringItemType | J22: DURATION
B23: [D818005] 31. 특수관계자 거래 | 31. Related party transactions | C23: 특수관계자 지급보증에 대한 공시 | D23: ifrs-full | E23: FinancialAssetsPledgedAsCollateralForLiabilitiesOrContingentLiabilities | F23: 부채나 우발부채에 대한 담보로 제공된 금융자산 | G23: Financial assets pledged as collateral for liabilities or contingent liabilities | I23: xbrli:monetaryItemType | J23: INSTANT

Sheet Checklist_4-6
B2: 특수관계자 관련 전용요소 검토 (2)
B3: ※ XBRL Checklist 결과는 참고 목적으로 제공드리는 내역으로, 텍사노미 구조와 관련된 리뷰는 CoE 업무 Scope에 포함되지 않습니다.
B11: 0 | C11: 개 항목이 추출되었습니다.
B13: Role Definition | C13: TABLE NAME | D13: Prefix | E13: Name | F13: Label(KO) | G13: Label(EN) | H13: Label Role | I13: DataType | J13: Period

Sheet Checklist_5-1
B2: 이자율, 할인율 속성 검토
B3: ※ XBRL Checklist 결과는 참고 목적으로 제공드리는 내역으로, 텍사노미 구조와 관련된 리뷰는 CoE 업무 Scope에 포함되지 않습니다.
L4: Reference - 금감원 가이드 151page
B11: 38 | C11: 개 항목이 추출되었습니다.
B13: Role Definition | C13: TABLE NAME | D13: Prefix | E13: Name | F13: Label(KO) | G13: Label(EN) | H13: Label Role | I13: DataType | J13: Period
B14: [D822420] 8. 매출채권 및 기타채권 | 8. Trade and other receivables | C14: 연체되거나 손상된 매출채권 및 기타채권에 대한 공시 [표] | D14: ifrs-full | E14: ExpectedCreditLossRate | F14: 기대신용손실율 | G14: Expected credit loss rate | I14: num:percentItemType | J14: INSTANT
B15: [D822400] 19. 단기차입금 | 19. Short-term borrowings | C15: 단기차입금의 상세내역 | D15: ifrs-full | E15: BorrowingsInterestRate | F15: 차입금, 이자율 | G15: Borrowings, interest rate | I15: num:percentItemType | J15: INSTANT
B16: [D834480] 21. 퇴직급여제도 | 21. Employee benefit plans | C16: 사외적립자산의 공정가치에 대한 공시 [표] | D16: ifrs-full | E16: DebtInstrumentsPercentageContributedToFairValueOfPlanAssets | F16: 채무상품, 사외적립자산의 공정가치에서 차지하는 비율 | G16: Debt instruments, percentage contributed to fair value of plan assets | I16: num:percentItemType | J16: INSTANT
B17: [D834480] 21. 퇴직급여제도 | 21. Employee benefit plans | C17: 보험수리적가정에 대한 공시 | D17: ifrs-full | E17: ActuarialAssumptionOfDiscountRates | F17: 할인율에 대한 보험수리적 가정 | G17: Actuarial assumption of discount rates | I17: num:percentItemType | J17: INSTANT
B18: [D834480] 21. 퇴직급여제도 | 21. Employee benefit plans | C18: 보험수리적가정에 대한 공시 | D18: ifrs-full | E18: ActuarialAssumptionOfExpectedRatesOfSalaryIncreases | F18: 미래임금상승률에 대한 보험수리적 가정 | G18: Actuarial assumption of expected rates of salary increases | I18: num:percentItemType | J18: INSTANT
B19: [D834480] 21. 퇴직급여제도 | 21. Employee benefit plans | C19: 보험수리적가정의 민감도분석에 대한 공시 [표] | D19: ifrs-full | E19: PercentageOfReasonablyPossibleIncreaseInActuarialAssumption | F19: 보험수리적가정의 합리적인 범위 내에서의 발생가능한 증가율 | G19: Percentage of reasonably possible increase in actuarial assumption | I19: num:percentItemType | J19: INSTANT
B20: [D834480] 21. 퇴직급여제도 | 21. Employee benefit plans | C20: 보험수리적가정의 민감도분석에 대한 공시 [표] | D20: ifrs-full | E20: PercentageOfReasonablyPossibleDecreaseInActuarialAssumption | F20: 보험수리적가정의 합리적인 범위 내에서의 발생가능한 감소율 | G20: Percentage of reasonably possible decrease in actuarial assumption | I20: num:percentItemType | J20: INSTANT
B21: [D834120] 23. 주식기준보상 | 23. Share-based payment arrangements | C21: 주식선택권 공정가치 측정에 사용된 주요 가정의 공시 | D21: ifrs-full | E21: DescriptionOfRiskFreeInterestRateShareOptionsGranted | F21: 무위험이자율, 부여한 주식선택권 | G21: Risk free interest rate, share options granted | I21: num:percentItemType | J21: DURATION
B22: [D834120] 23. 주식기준보상 | 23. Share-based payment arrangements | C22: 주식선택권 공정가치 측정에 사용된 주요 가정의 공시 | D22: ifrs-full | E22: DescriptionOfExpectedVolatilityShareOptionsGranted | F22: 기대주가변동성, 부여한 주식선택권 | G22: Expected volatility, share options granted | I22: num:percentItemType | J22: DURATION
B23: [D861310] 24. 배당금 | 24. Dividends | C23: 배당금에 대한 공시 [표] | D23: dart | E23: DividendsRateforOrdinarySharesPerShare | F23: 보통주 주당 배당률 | G23: Dividend rate for ordinary shares per share | I23: num:percentItemType | J23: DURATION
B24: [D861310] 24. 배당금 | 24. Dividends | C24: 배당금에 대한 공시 [표] | D24: entity00825959 | E24: DividendPayoutRatioOfDisclosureOfDividendsPaidLineItemsOfDisclosureOfDividendsPaidTableOfItems | F24: 배당성향 | G24: Dividend payout ratio | I24: percentItemType | J24: INSTANT
B25: [D861310] 24. 배당금 | 24. Dividends | C25: 배당금에 대한 공시 [표] | D25: entity00825959 | E25: DividendYieldOfDisclosureOfDividendsPaidLineItemsOfDisclosureOfDividendsPaidTableOfItems | F25: 배당수익률 | G25: Dividend yield | I25: percentItemType | J25: INSTANT
... B51: [D832415] 36. 종속기업 및 관계기업투자주식의 손상검사 | 36. Impairment testing of investments in subsidiaries and associates | C51: 추정 기간 동안 사용가치 계산에 사용된 주된 가정치의 공시 | D51: ifrs-full | E51: DescriptionOfDiscountRatesAppliedToCashFlowProjections | F51: 미래현금흐름 추정치에 적용된 할인율 | G51: Discount rate applied to cash flow projections | I51: num:percentItemType | J51: INSTANT

Sheet Checklist_5-2
B2: 주식 수 속성 검토
B3: ※ XBRL Checklist 결과는 참고 목적으로 제공드리는 내역으로, 텍사노미 구조와 관련된 리뷰는 CoE 업무 Scope에 포함되지 않습니다.
L4: Reference - 금감원 가이드 151page
B11: 2 | C11: 개 항목이 추출되었습니다.
B13: Role Definition | C13: TABLE NAME | D13: Prefix | E13: Name | F13: Label(KO) | G13: Label(EN) | H13: Label Role | I13: DataType | J13: Period
B14: [D838000] 30. 주당손익 | 30. Earnings per share | C14: 주당이익 [표] | D14: ifrs-full | E14: WeightedAverageShares | F14: 가중평균유통보통주식수(단위:주) | G14: Weighted average number of ordinary shares used in calculating basic earnings per share(Unit:share) | H14: terseLabel | I14: xbrli:sharesItemType | J14: DURATION
B15: [D838005] 29. 주당손익 | 29. Earnings per share | C15: 주당이익 [표] | D15: ifrs-full | E15: WeightedAverageShares | F15: 가중평균유통보통주식수(단위:주) | G15: Weighted average number of ordinary shares used in calculating basic earnings per share(Unit:share) | H15: terseLabel | I15: xbrli:sharesItemType | J15: DURATION

Sheet Checklist_5-3
B2: 이연법인세부채(자산) 검토
B3: ※ XBRL Checklist 결과는 참고 목적으로 제공드리는 내역으로, 텍사노미 구조와 관련된 리뷰는 CoE 업무 Scope에 포함되지 않습니다.
L4: Reference - 금감원 가이드 253page
B11: 4 | C11: 개 항목이 추출되었습니다.
B13: Role Definition | C13: TABLE NAME | D13: Prefix | E13: Name | F13: Label(KO) | G13: Label(EN) | H13: Label Role | I13: DataType | J13: Period
B14: [D835110] 29. 법인세 | 29. Income taxes | C14: 일시적차이, 미사용 세무상 결손금과 미사용 세액공제에 대한 공시 [표] | D14: ifrs-full | E14: DeferredTaxLiabilityAsset | F14: 기초 이연법인세부채(자산) | G14: Deferred tax liability (asset) at beginning of period | H14: periodStartLabel | I14: xbrli:monetaryItemType | J14: INSTANT
B15: [D835110] 29. 법인세 | 29. Income taxes | C15: 일시적차이, 미사용 세무상 결손금과 미사용 세액공제에 대한 공시 [표] | D15: ifrs-full | E15: DeferredTaxLiabilityAsset | F15: 기말 이연법인세부채(자산) | G15: Deferred tax liability (asset) at beginning of period | H15: periodEndLabel | I15: xbrli:monetaryItemType | J15: INSTANT
B16: [D835115] 28. 법인세 | 28. Income taxes | C16: 일시적차이, 미사용 세무상 결손금과 미사용 세액공제에 대한 공시 [표] | D16: ifrs-full | E16: DeferredTaxLiabilityAsset | F16: 기초 이연법인세부채(자산) | G16: Deferred tax liability (asset) at beginning of period | H16: periodStartLabel | I16: xbrli:monetaryItemType | J16: INSTANT
B17: [D835115] 28. 법인세 | 28. Income taxes | C17: 일시적차이, 미사용 세무상 결손금과 미사용 세액공제에 대한 공시 [표] | D17: ifrs-full | E17: DeferredTaxLiabilityAsset | F17: 기말 이연법인세부채(자산) | G17: Deferred tax liability (asset) at beginning of period | H17: periodEndLabel | I17: xbrli:monetaryItemType | J17: INSTANT

Sheet Checklist_5-4
B2: 기본주당이익/희석주당이익 속성 검토
B3: ※ XBRL Checklist 결과는 참고 목적으로 제공드리는 내역으로, 텍사노미 구조와 관련된 리뷰는 CoE 업무 Scope에 포함되지 않습니다.
L4: Reference - 금감원 가이드 259page
B11: 0 | C11: 개 항목이 추출되었습니다.
B13: Role Definition | C13: TABLE NAME | D13: Prefix | E13: Name | F13: Label(KO) | G13: Label(EN) | H13: Label Role | I13: DataType | J13: Period

Sheet Checklist_5-5
B2: 기초/기말 영문명 검토
B3: ※ XBRL Checklist 결과는 참고 목적으로 제공드리는 내역으로, 텍사노미 구조와 관련된 리뷰는 CoE 업무 Scope에 포함되지 않습니다.
B11: 102 | C11: 개 항목이 추출되었습니다.
B13: Role Definition | C13: TABLE NAME | D13: Prefix | E13: Name | F13: Label(KO) | G13: Label(EN) | H13: Label Role | I13: DataType | J13: Period
B14: [D610000] 자본변동표 - 연결 | Statement of changes in equity - Consolidated financial statements | C14: 자본변동표 [표] | D14: dart | E14: EquityAtBeginningOfPeriod | F14: 기초자본 | G14: Equity at beginning of period | I14: xbrli:monetaryItemType | J14: DURATION
B15: [D610000] 자본변동표 - 연결 | Statement of changes in equity - Consolidated financial statements | C15: 자본변동표 [표] | D15: ifrs-full | E15: Equity | F15: 기말자본 | G15: Equity at end of period | H15: periodEndLabel | I15: xbrli:monetaryItemType | J15: INSTANT
B16: [D520000] 현금흐름표, 간접법 - 연결 | Statement of cash flows, indirect method - Consolidated financial statements | C16: 현금흐름표, 간접법 - 연결 | D16: dart | E16: CashAndCashEquivalentsAtBeginningOfPeriodCf | F16: 기초현금및현금성자산 | G16: Cash and cash equivalents at beginning of period | I16: xbrli:monetaryItemType | J16: INSTANT
B17: [D520000] 현금흐름표, 간접법 - 연결 | Statement of cash flows, indirect method - Consolidated financial statements | C17: 현금흐름표, 간접법 - 연결 | D17: dart | E17: CashAndCashEquivalentsAtEndOfPeriodCf | F17: 기말현금및현금성자산 | G17: Cash and cash equivalents at end of period | I17: xbrli:monetaryItemType | J17: INSTANT
B18: [D823000] 5. 금융상품 공정가치 | 5. Fair value of financial instruments | C18: 공정가치로 측정하는 금융상품 중 수준3으로 분류된 항목의 변동내역 | D18: ifrs-full | E18: Assets | F18: 기초 자산 | G18: Assets at beginning of period | H18: periodStartLabel | I18: xbrli:monetaryItemType | J18: INSTANT
B19: [D823000] 5. 금융상품 공정가치 | 5. Fair value of financial instruments | C19: 공정가치로 측정하는 금융상품 중 수준3으로 분류된 항목의 변동내역 | D19: ifrs-full | E19: Assets | F19: 기말 자산 | G19: Assets at ending of period | H19: periodEndLabel | I19: xbrli:monetaryItemType | J19: INSTANT
B20: [D822420] 8. 매출채권 및 기타채권 | 8. Trade and other receivables | C20: 매출채권 및 기타채권 손실충당금과 총장부금액의 변동에 대한 공시 [표] | D20: ifrs-full | E20: FinancialAssets | F20: 기초금융자산 | G20: Financial assets at beginning of period | H20: periodStartLabel | I20: xbrli:monetaryItemType | J20: INSTANT
B21: [D822420] 8. 매출채권 및 기타채권 | 8. Trade and other receivables | C21: 매출채권 및 기타채권 손실충당금과 총장부금액의 변동에 대한 공시 [표] | D21: ifrs-full | E21: FinancialAssets | F21: 기말금융자산 | G21: Financial assets at end of period | H21: periodEndLabel | I21: xbrli:monetaryItemType | J21: INSTANT
B22: [D826380] 9. 재고자산 | 9. Inventories | C22: 재고자산평가충당금 변동내역 | D22: ifrs-full | E22: Inventories | F22: 유동재고자산 기초 | G22: Beginning of Current inventories | H22: periodStartLabel | I22: xbrli:monetaryItemType | J22: INSTANT
B23: [D826380] 9. 재고자산 | 9. Inventories | C23: 재고자산평가충당금 변동내역 | D23: ifrs-full | E23: Inventories | F23: 유동재고자산 기말 | G23: Ending of Current inventories | H23: periodEndLabel | I23: xbrli:monetaryItemType | J23: INSTANT
B24: [D822100] 11. 유형자산 | 11. Property, plant and equipment | C24: 유형자산에 대한 세부 정보 공시 | D24: ifrs-full | E24: PropertyPlantAndEquipment | F24: 기초 유형자산 | G24: Property, plant and equipment at beginning of period | H24: periodStartLabel | I24: xbrli:monetaryItemType | J24: INSTANT
B25: [D822100] 11. 유형자산 | 11. Property, plant and equipment | C25: 유형자산에 대한 세부 정보 공시 | D25: ifrs-full | E25: PropertyPlantAndEquipment | F25: 기말 유형자산 | G25: Property, plant and equipment at ending of period | H25: periodEndLabel | I25: xbrli:monetaryItemType | J25: INSTANT
B26: [D822100] 11. 유형자산 | 11. Property, plant and equipment | C26: 유형자산 총장부금액, 감가상각누계액, 정부보조금 변동에 대한 공시 | D26: ifrs-full | E26: PropertyPlantAndEquipment | F26: 기초 유형자산 | G26: Property, plant and equipment at beginning of period | H26: periodStartLabel | I26: xbrli:monetaryItemType | J26: INSTANT
B27: [D822100] 11. 유형자산 | 11. Property, plant and equipment | C27: 유형자산 총장부금액, 감가상각누계액, 정부보조금 변동에 대한 공시 | D27: ifrs-full | E27: PropertyPlantAndEquipment | F27: 기말 유형자산 | G27: Property, plant and equipment at ending of period | H27: periodEndLabel | I27: xbrli:monetaryItemType | J27: INSTANT
B28: [D825100] 12. 투자부동산 | 12. Investment property | C28: 투자부동산에 대한 세부 정보 공시 [표] | D28: ifrs-full | E28: InvestmentProperty | F28: 기초 투자부동산 | G28: Investment property at beginning of period | H28: periodStartLabel | I28: xbrli:monetaryItemType | J28: INSTANT
B29: [D825100] 12. 투자부동산 | 12. Investment property | C29: 투자부동산에 대한 세부 정보 공시 [표] | D29: ifrs-full | E29: InvestmentProperty | F29: 기말 투자부동산 | G29: Investment property at ending of period | H29: periodEndLabel | I29: xbrli:monetaryItemType | J29: INSTANT
... B57: [D851100] 31. 현금흐름표 | 31. Cash flow statement | C57: 재무활동에서 생기는 부채의 조정에 관한 공시 [표] | D57: ifrs-full | E57: LiabilitiesArisingFromFinancingActivities | F57: 재무활동에서 생기는 기말 부채 | G57: Liabilities arising from financing activities at end of period | H57: periodEndLabel | I57: xbrli:monetaryItemType | J57: INSTANT
B58: [D818000] 32. 특수관계자 거래 | 32. Related party transactions | C58: 특수관계자 자금거래에 관한 공시 [표] | D58: dart | E58: LoanTransactionsBetweenEntityRelatedPartyLending | F58: 대여거래, 대여 | G58: Loan transactions, lending | I58: xbrli:monetaryItemType | J58: INSTANT
B59: [D831150] 35. 고객과의 계약에서 생기는 수익 | 35. Revenue from contracts with customers | C59: 계약자산 및 계약부채 | D59: ifrs-full | E59: RevenueThatWasIncludedInContractLiabilityBalanceAtBeginningOfPeriod | F59: 기초 계약부채 잔액 중 인식한 수익 | G59: Revenue that was included in contract liability balance at beginning of period | I59: xbrli:monetaryItemType | J59: DURATION
B60: [D822380] 36. 위험관리 | 36. Risk management | C60: 외화금융자산의 통화별 내역 [표] | D60: entity00825959 | E60: FinancialAssetsDenominatedInForeignCurrencyOriginalCurrencyusdOfDetailsOfFinancialAssetsDenominatedInForeignCurrencyLineItemsOfDetailsOfFinancialAssetsDenominatedInForeignCurrencyTableOfItems | F60: 외화금융자산, 기초통화금액 USD | G60: Financial Assets Denominated In Foreign Currency Original CurrencyUSD | I60: monetaryItemType | J60: INSTANT
B61: [D822380] 36. 위험관리 | 36. Risk management | C61: 외화금융자산의 통화별 내역 [표] | D61: entity00825959 | E61: FinancialAssetsDenominatedInForeignCurrencyOriginalCurrencyeurOfDetailsOfFinancialAssetsDenominatedInForeignCurrencyLineItemsOfDetailsOfFinancialAssetsDenominatedInForeignCurrencyTableOfItems | F61: 외화금융자산, 기초통화금액 EUR | G61: Financial Assets Denominated In Foreign Currency Original CurrencyEUR | I61: monetaryItemType | J61: INSTANT
B62: [D822380] 36. 위험관리 | 36. Risk management | C62: 외화금융자산의 통화별 내역 [표] | D62: entity00825959 | E62: FinancialAssetsDenominatedInForeignCurrencyOriginalCurrencycadOfDetailsOfFinancialAssetsDenominatedInForeignCurrencyLineItemsOfDetailsOfFinancialAssetsDenominatedInForeignCurrencyTableOfItems | F62: 외화금융자산, 기초통화금액 CAD | G62: Financial Assets Denominated In Foreign Currency Original CurrencyCAD | I62: monetaryItemType | J62: INSTANT
B63: [D822380] 36. 위험관리 | 36. Risk management | C63: 외화금융자산의 통화별 내역 [표] | D63: entity00825959 | E63: FinancialAssetsDenominatedInForeignCurrencyOriginalCurrencycnyOfDetailsOfFinancialAssetsDenominatedInForeignCurrencyLineItemsOfDetailsOfFinancialAssetsDenominatedInForeignCurrencyTableOfItems | F63: 외화금융자산, 기초통화금액 CNY | G63: Financial Assets Denominated In Foreign Currency Original CurrencyCNY | I63: monetaryItemType | J63: INSTANT
B64: [D822380] 36. 위험관리 | 36. Risk management | C64: 외화금융자산의 통화별 내역 [표] | D64: entity00825959 | E64: FinancialAssetsDenominatedInForeignCurrencyOriginalCurrencyvndOfDetailsOfFinancialAssetsDenominatedInForeignCurrencyLineItemsOfDetailsOfFinancialAssetsDenominatedInForeignCurrencyTableOfItems | F64: 외화금융자산, 기초통화금액 VND | G64: Financial Assets Denominated In Foreign Currency Original CurrencyVND | I64: monetaryItemType | J64: INSTANT
B65: [D822380] 36. 위험관리 | 36. Risk management | C65: 외화금융자산의 통화별 내역 [표] | D65: entity00825959 | E65: FinancialAssetsDenominatedInForeignCurrencyOriginalCurrencyinrOfDetailsOfFinancialAssetsDenominatedInForeignCurrencyLineItemsOfDetailsOfFinancialAssetsDenominatedInForeignCurrencyTableOfItems | F65: 외화금융자산, 기초통화금액 INR | G65: Financial Assets Denominated In Foreign Currency Original CurrencyINR | I65: monetaryItemType | J65: INSTANT
B66: [D822380] 36. 위험관리 | 36. Risk management | C66: 외화금융부채의 통화별 내역 [표] | D66: entity00825959 | E66: FinancialLiabilitiesDenominatedInForeignCurrencyOriginalCurrencyusdOfDetailsOfFinancialLiabilitiesDenominatedInForeignCurrencyLineItemsOfDetailsOfFinancialLiabilitiesDenominatedInForeignCurrencyTableOfItems | F66: 외화금융부채, 기초통화금액USD | G66: Financial liabilities denominated in foreign currency, original currencyUSD | I66: monetaryItemType | J66: INSTANT
B67: [D822380] 36. 위험관리 | 36. Risk management | C67: 외화금융부채의 통화별 내역 [표] | D67: entity00825959 | E67: FinancialLiabilitiesDenominatedInForeignCurrencyOriginalCurrencycnyOfDetailsOfFinancialLiabilitiesDenominatedInForeignCurrencyLineItemsOfDetailsOfFinancialLiabilitiesDenominatedInForeignCurrencyTableOfItems | F67: 외화금융부채, 기초통화금액 CNY | G67: Financial liabilities denominated in foreign currency, original currencyCNY | I67: monetaryItemType | J67: INSTANT
B68: [D822380] 36. 위험관리 | 36. Risk management | C68: 외화금융부채의 통화별 내역 [표] | D68: entity00825959 | E68: FinancialLiabilitiesDenominatedInForeignCurrencyOriginalCurrencyvndOfDetailsOfFinancialLiabilitiesDenominatedInForeignCurrencyLineItemsOfDetailsOfFinancialLiabilitiesDenominatedInForeignCurrencyTableOfItems | F68: 외화금융부채, 기초통화금액 VND | G68: Financial liabilities denominated in foreign currency, original currencyVND | I68: monetaryItemType | J68: INSTANT
B69: [D822380] 36. 위험관리 | 36. Risk management | C69: 외화금융부채의 통화별 내역 [표] | D69: entity00825959 | E69: FinancialLiabilitiesDenominatedInForeignCurrencyOriginalCurrencyinrOfDetailsOfFinancialLiabilitiesDenominatedInForeignCurrencyLineItemsOfDetailsOfFinancialLiabilitiesDenominatedInForeignCurrencyTableOfItems | F69: 외화금융부채, 기초통화금액 INR | G69: Financial liabilities denominated in foreign currency, original currencyINR | I69: monetaryItemType | J69: INSTANT
B70: [D610005] 자본변동표 - 별도 | Statement of changes in equity - Separate financial statements | C70: 자본변동표 [표] | D70: dart | E70: EquityAtBeginningOfPeriod | F70: 기초자본 | G70: Equity at beginning of period | I70: xbrli:monetaryItemType | J70: DURATION
B71: [D610005] 자본변동표 - 별도 | Statement of changes in equity - Separate financial statements | C71: 자본변동표 [표] | D71: ifrs-full | E71: Equity | F71: 기말자본 | G71: Equity at end of period | H71: periodEndLabel | I71: xbrli:monetaryItemType | J71: INSTANT
B72: [D520005] 현금흐름표, 간접법 - 별도 | Statement of cash flows, indirect method - Separate financial statements | C72: 현금흐름표, 간접법 - 별도 | D72: dart | E72: CashAndCashEquivalentsAtBeginningOfPeriodCf | F72: 기초현금및현금성자산 | G72: Cash and cash equivalents at beginning of period | I72: xbrli:monetaryItemType | J72: INSTANT
B73: [D520005] 현금흐름표, 간접법 - 별도 | Statement of cash flows, indirect method - Separate financial statements | C73: 현금흐름표, 간접법 - 별도 | D73: dart | E73: CashAndCashEquivalentsAtEndOfPeriodCf | F73: 기말현금및현금성자산 | G73: Cash and cash equivalents at end of period | I73: xbrli:monetaryItemType | J73: INSTANT
B74: [D823005] 5. 금융상품 공정가치 | 5. Fair value of financial instruments | C74: 공정가치로 측정하는 금융상품 중 수준3으로 분류된 항목의 변동내역 | D74: ifrs-full | E74: Assets | F74: 기초 자산 | G74: Assets at beginning of period | H74: periodStartLabel | I74: xbrli:monetaryItemType | J74: INSTANT
B75: [D823005] 5. 금융상품 공정가치 | 5. Fair value of financial instruments | C75: 공정가치로 측정하는 금융상품 중 수준3으로 분류된 항목의 변동내역 | D75: ifrs-full | E75: Assets | F75: 기말 자산 | G75: Assets at ending of period | H75: periodEndLabel | I75: xbrli:monetaryItemType | J75: INSTANT
B76: [D822425] 8. 매출채권 및 기타채권 | 8. Trade and other receivables | C76: 매출채권 및 기타채권 손실충당금과 총장부금액의 변동에 대한 공시 [표] | D76: ifrs-full | E76: FinancialAssets | F76: 기초금융자산 | G76: Financial assets at beginning of period | H76: periodStartLabel | I76: xbrli:monetaryItemType | J76: INSTANT
B77: [D822425] 8. 매출채권 및 기타채권 | 8. Trade and other receivables | C77: 매출채권 및 기타채권 손실충당금과 총장부금액의 변동에 대한 공시 [표] | D77: ifrs-full | E77: FinancialAssets | F77: 기말금융자산 | G77: Financial assets at end of period | H77: periodEndLabel | I77: xbrli:monetaryItemType | J77: INSTANT
B78: [D826385] 9. 재고자산 | 9. Inventories | C78: 재고자산평가충당금 변동내역 | D78: ifrs-full | E78: Inventories | F78: 유동재고자산 기초 | G78: Beginning of Current inventories | H78: periodStartLabel | I78: xbrli:monetaryItemType | J78: INSTANT
B79: [D826385] 9. 재고자산 | 9. Inventories | C79: 재고자산평가충당금 변동내역 | D79: ifrs-full | E79: Inventories | F79: 유동재고자산 기말 | G79: Ending of Current inventories | H79: periodEndLabel | I79: xbrli:monetaryItemType | J79: INSTANT
B80: [D822105] 11. 유형자산 | 11. Property, plant and equipment | C80: 유형자산에 대한 세부 정보 공시 | D80: ifrs-full | E80: PropertyPlantAndEquipment | F80: 기초 유형자산 | G80: Property, plant and equipment at beginning of period | H80: periodStartLabel | I80: xbrli:monetaryItemType | J80: INSTANT
B81: [D822105] 11. 유형자산 | 11. Property, plant and equipment | C81: 유형자산에 대한 세부 정보 공시 | D81: ifrs-full | E81: PropertyPlantAndEquipment | F81: 기말 유형자산 | G81: Property, plant and equipment at ending of period | H81: periodEndLabel | I81: xbrli:monetaryItemType | J81: INSTANT
B82: [D822105] 11. 유형자산 | 11. Property, plant and equipment | C82: 유형자산 총장부금액, 감가상각누계액, 정부보조금 변동에 대한 공시 | D82: ifrs-full | E82: PropertyPlantAndEquipment | F82: 기초 유형자산 | G82: Property, plant and equipment at beginning of period | H82: periodStartLabel | I82: xbrli:monetaryItemType | J82: INSTANT
B83: [D822105] 11. 유형자산 | 11. Property, plant and equipment | C83: 유형자산 총장부금액, 감가상각누계액, 정부보조금 변동에 대한 공시 | D83: ifrs-full | E83: PropertyPlantAndEquipment | F83: 기말 유형자산 | G83: Property, plant and equipment at ending of period | H83: periodEndLabel | I83: xbrli:monetaryItemType | J83: INSTANT
B84: [D825105] 12. 투자부동산 | 12. Investment property | C84: 투자부동산에 대한 세부 정보 공시 [표] | D84: ifrs-full | E84: InvestmentProperty | F84: 기초 투자부동산 | G84: Investment property at beginning of period | H84: periodStartLabel | I84: xbrli:monetaryItemType | J84: INSTANT
B85: [D825105] 12. 투자부동산 | 12. Investment property | C85: 투자부동산에 대한 세부 정보 공시 [표] | D85: ifrs-full | E85: InvestmentProperty | F85: 기말 투자부동산 | G85: Investment property at ending of period | H85: periodEndLabel | I85: xbrli:monetaryItemType | J85: INSTANT
... B109: [D851105] 30. 현금흐름표 | 30. Cash flow statement | C109: 재무활동에서 생기는 부채의 조정에 관한 공시 [표] | D109: ifrs-full | E109: LiabilitiesArisingFromFinancingActivities | F109: 재무활동에서 생기는 기말 부채 | G109: Liabilities arising from financing activities at end of period | H109: periodEndLabel | I109: xbrli:monetaryItemType | J109: INSTANT
B110: [D818005] 31. 특수관계자 거래 | 31. Related party transactions | C110: 특수관계자 자금거래에 관한 공시 [표] | D110: dart | E110: LoanTransactionsBetweenEntityRelatedPartyLending | F110: 대여거래, 대여 | G110: Loan transactions, lending | I110: xbrli:monetaryItemType | J110: INSTANT
B111: [D831155] 34. 고객과의 계약에서 생기는 수익 | 34. Revenue from contracts with customers | C111: 계약자산 및 계약부채 | D111: ifrs-full | E111: RevenueThatWasIncludedInContractLiabilityBalanceAtBeginningOfPeriod | F111: 기초 계약부채 잔액 중 인식한 수익 | G111: Revenue that was included in contract liability balance at beginning of period | I111: xbrli:monetaryItemType | J111: DURATION
B112: [D822385] 35. 위험관리 | 35. Risk management | C112: 외화금융자산의 통화별 내역 [표] | D112: entity00825959 | E112: FinancialAssetsDenominatedInForeignCurrencyOriginalCurrencyusdOfDetailsOfFinancialAssetsDenominatedInForeignCurrencyLineItemsOfDetailsOfFinancialAssetsDenominatedInForeignCurrencyTableOfItems | F112: 외화금융자산, 기초통화금액 USD | G112: Financial Assets Denominated In Foreign Currency Original CurrencyUSD | I112: monetaryItemType | J112: INSTANT
B113: [D822385] 35. 위험관리 | 35. Risk management | C113: 외화금융자산의 통화별 내역 [표] | D113: entity00825959 | E113: FinancialAssetsDenominatedInForeignCurrencyOriginalCurrencycnyOfDetailsOfFinancialAssetsDenominatedInForeignCurrencyLineItemsOfDetailsOfFinancialAssetsDenominatedInForeignCurrencyTableOfItems | F113: 외화금융자산, 기초통화금액 CNY | G113: Financial Assets Denominated In Foreign Currency Original CurrencyCNY | I113: monetaryItemType | J113: INSTANT
B114: [D822385] 35. 위험관리 | 35. Risk management | C114: 외화금융부채의 통화별 내역 [표] | D114: entity00825959 | E114: FinancialLiabilitiesDenominatedInForeignCurrencyOriginalCurrencyusdOfDetailsOfFinancialLiabilitiesDenominatedInForeignCurrencyLineItemsOfDetailsOfFinancialLiabilitiesDenominatedInForeignCurrencyTableOfItems | F114: 외화금융부채, 기초통화금액USD | G114: Financial liabilities denominated in foreign currency, original currencyUSD | I114: monetaryItemType | J114: INSTANT
B115: [D822385] 35. 위험관리 | 35. Risk management | C115: 외화금융부채의 통화별 내역 [표] | D115: entity00825959 | E115: FinancialLiabilitiesDenominatedInForeignCurrencyOriginalCurrencycnyOfDetailsOfFinancialLiabilitiesDenominatedInForeignCurrencyLineItemsOfDetailsOfFinancialLiabilitiesDenominatedInForeignCurrencyTableOfItems | F115: 외화금융부채, 기초통화금액 CNY | G115: Financial liabilities denominated in foreign currency, original currencyCNY | I115: monetaryItemType | J115: INSTANT

Sheet Checklist_5-6
B2: 단위미사용 검토
B3: ※ XBRL Checklist 결과는 참고 목적으로 제공드리는 내역으로, 텍사노미 구조와 관련된 리뷰는 CoE 업무 Scope에 포함되지 않습니다.
B11: 18 | C11: 개 항목이 추출되었습니다.
B13: Role Definition | C13: TABLE NAME | D13: 단위표시/미표시
B14: [D823000] 5. 금융상품 공정가치 | 5. Fair value of financial instruments | C14: 공정가치 서열체계의 수준 | D14: 단위미표시
B15: [D822100] 11. 유형자산 | 11. Property, plant and equipment | C15: 담보제공 유형자산에 대한 공시 | D15: 단위미표시
B16: [D832610] 13. 사용권자산 | 13. Right-of-use assets | C16: 13. 사용권자산 | D16: 단위미표시
B17: [D834480] 21. 퇴직급여제도 | 21. Employee benefit plans | C17: 보험수리적가정에 대한 공시 | D17: 단위미표시
B18: [D834120] 23. 주식기준보상 | 23. Share-based payment arrangements | C18: 주식선택권 내역의 공시 | D18: 단위미표시
B19: [D834120] 23. 주식기준보상 | 23. Share-based payment arrangements | C19: 주식선택권 상세내역의 공시 | D19: 단위미표시
B20: [D818000] 32. 특수관계자 거래 | 32. Related party transactions | C20: 특수관계자 현황의 공시 | D20: 단위미표시
B21: [D822380] 36. 위험관리 | 36. Risk management | C21: 금융상품에서 발생하는 위험의 성격과 정도에 대한 공시 [표] | D21: 단위미표시
B22: [D832410] 37. 종속기업의 현금창출단위에 대한 손상검사 | 37. Impairment testing of cash-generating units of subsidiaries | C22: 추정 기간 동안 사용가치 계산에 사용된 주된 가정치의 공시 | D22: 단위미표시
B23: [D832410] 37. 종속기업의 현금창출단위에 대한 손상검사 | 37. Impairment testing of cash-generating units of subsidiaries | C23: 현금창출단위의 정보에 대한 공시 [표] | D23: 단위미표시
B24: [D823005] 5. 금융상품 공정가치 | 5. Fair value of financial instruments | C24: 공정가치 서열체계의 수준 | D24: 단위미표시
... B31: [D832415] 36. 종속기업 및 관계기업투자주식의 손상검사 | 36. Impairment testing of investments in subsidiaries and associates | C31: 현금창출단위의 정보에 대한 공시 [표] | D31: 단위미표시

Sheet Checklist_6-1
B2: 축 확장 검토
B3: ※ XBRL Checklist 결과는 참고 목적으로 제공드리는 내역으로, 텍사노미 구조와 관련된 리뷰는 CoE 업무 Scope에 포함되지 않습니다.
B11: 0 | C11: 개 항목이 추출되었습니다.
B13: Role Definition | C13: TABLE NAME | D13: Prefix | E13: Name | F13: Label(KO) | G13: Label(EN) | H13: Label Role | I13: DataType | J13: Period

Sheet Checklist_6-2
B2: 멤버열 확장 검토
B3: ※ XBRL Checklist 결과는 참고 목적으로 제공드리는 내역으로, 텍사노미 구조와 관련된 리뷰는 CoE 업무 Scope에 포함되지 않습니다.
B11: 0 | C11: 개 항목이 추출되었습니다.
B13: Role Definition | C13: TABLE NAME | D13: Prefix | E13: Name | F13: Label(KO) | G13: Label(EN) | H13: Label Role | I13: DataType | J13: Period

Sheet Checklist_6-3
B2: Duration / Instant 속성 검토
B3: ※ XBRL Checklist 결과는 참고 목적으로 제공드리는 내역으로, 텍사노미 구조와 관련된 리뷰는 CoE 업무 Scope에 포함되지 않습니다.
B11: 150 | C11: 개 항목이 추출되었습니다.
B13: Role Definition | C13: TABLE NAME | D13: Prefix | E13: Name | F13: Label(KO) | G13: Label(EN) | H13: Label Role | I13: DataType | J13: Period
B14: [D520000] 현금흐름표, 간접법 - 연결 | Statement of cash flows, indirect method - Consolidated financial statements | C14: 현금흐름표, 간접법 - 연결 | D14: entity00825959 | E14: DecreaseInCurrentPortionOfLongTermLoansReceivableOfCashFlowsFromUsedInInvestingActivities | F14: 유동성장기대여금의 감소 | G14: Decrease in current portion of long-term loans receivable | I14: monetaryItemType | J14: DURATION
B15: [D520000] 현금흐름표, 간접법 - 연결 | Statement of cash flows, indirect method - Consolidated financial statements | C15: 현금흐름표, 간접법 - 연결 | D15: entity00825959 | E15: CashInflowsFromSubleasesOfCashFlowsFromUsedInInvestingActivities | F15: 전대리스 현금유입 | G15: Cash inflows from subleases | I15: monetaryItemType | J15: DURATION
B16: [D826380] 9. 재고자산 | 9. Inventories | C16: 재고자산평가충당금 변동내역 | D16: entity00825959 | E16: RetirementsInventoriesOfMovementsInAllowanceForInventoryValuationLossesOfMovementsInAllowanceForInventoryValuationLossesTableOfItems | F16: 폐기, 재고자산 | G16: Retirements, inventories | H16: negatedLabel | I16: monetaryItemType | J16: DURATION
B17: [D826380] 9. 재고자산 | 9. Inventories | C17: 재고자산평가충당금 변동내역 | D17: entity00825959 | E17: ReplacementInventoriesOfMovementsInAllowanceForInventoryValuationLossesOfMovementsInAllowanceForInventoryValuationLossesTableOfItems | F17: 대체, 재고자산 | G17: Replacement, inventories | I17: monetaryItemType | J17: DURATION
B18: [D822100] 11. 유형자산 | 11. Property, plant and equipment | C18: 담보제공 유형자산에 대한 공시 | D18: entity00825959 | E18: DescriptionOfPropertyPlantAndEquipmentPledgedAsCollateralOfDisclosureOfPropertyPlantAndEquipmentPledgedAsCollateralLineItemsOfDisclosureOfPropertyPlantAndEquipmentPledgedAsCollateralTableOfItems | F18: 담보제공 유형자산에 대한 설명 | G18: Description of property, plant and equipment pledged as collateral | I18: stringItemType | J18: DURATION
B19: [D832610] 13. 사용권자산 | 13. Right-of-use assets | C19: 13. 사용권자산 | D19: entity00825959 | E19: InformationAboutTheNatureOfLeasingActivities | F19: 리스활동 특성에 대한 정보 | G19: Information about the nature of leasing activities | I19: stringItemType | J19: DURATION
B20: [D832610] 13. 사용권자산 | 13. Right-of-use assets | C20: 사용권자산에 대한 양적 정보 공시 [표] | D20: entity00825959 | E20: IncreaseDecreaseDueToReclassificationRightOfUseAssetsOfDisclosureOfQuantitativeInformationAboutRightOfUseAssetsLineItemsOfDisclosureOfQuantitativeInformationAboutRightofuseAssetsTableOfItems | F20: 대체에 따른 증가(감소), 사용권자산 | G20: Increase (decrease) due to reclassification, right‑of‑use assets | I20: monetaryItemType | J20: DURATION
B21: [D832610] 13. 사용권자산 | 13. Right-of-use assets | C21: 사용권자산 총장부금액, 감가상각누계액 변동에 대한 공시 | D21: entity00825959 | E21: IncreaseDecreaseDueToReclassificationRightOfUseAssetsOfDisclosureOfChangesInTheGrossCarryingAmountOfRightOfUseAssetsAndAccumulatedDepreciationLineItemsOfDisclosureOfChangesInTheGrossCarryingAmountOfRightOfUseAssetsAndAccumulatedDepreciationTableOfItems | F21: 대체에 따른 증가(감소), 사용권자산 | G21: Increase (decrease) due to reclassification, right‑of‑use assets | I21: monetaryItemType | J21: DURATION
B22: [D832620] 14. 리스부채 | 14. Lease liabilities | C22: 리스부채 분류에 대한 공시 | D22: entity00825959 | E22: DisclosureOnTheClassificationOfLeaseLiabilitiesAbstract | F22: 리스부채 분류에 대한 공시[ 개요 ] | G22: Disclosure on the classification of lease liabilities[ abstract ] | I22: stringItemType | J22: DURATION
B23: [D832620] 14. 리스부채 | 14. Lease liabilities | C23: 리스부채 분류에 대한 공시 | D23: entity00825959 | E23: DisclosureOnTheClassificationOfLeaseLiabilitiesLineItemsOfDisclosureOnTheClassificationOfLeaseLiabilitiesTableOfLineItems | F23: 리스부채 분류에 대한 공시 [ 항목 ] | G23: Disclosure on the classification of lease liabilities [line items] | I23: stringItemType | J23: DURATION
B24: [D832620] 14. 리스부채 | 14. Lease liabilities | C24: 리스부채 분류에 대한 공시 | D24: entity00825959 | E24: CurrentLeaseLiabilityOfDisclosureOnTheClassificationOfLeaseLiabilitiesLineItemsOfDisclosureOnTheClassificationOfLeaseLiabilitiesTableOfItems | F24: 유동 리스부채 | G24: Current lease liability | I24: monetaryItemType | J24: INSTANT
B25: [D832620] 14. 리스부채 | 14. Lease liabilities | C25: 리스부채 분류에 대한 공시 | D25: entity00825959 | E25: NonCurrentLeaseLiabilityOfDisclosureOnTheClassificationOfLeaseLiabilitiesLineItemsOfDisclosureOnTheClassificationOfLeaseLiabilitiesTableOfItems | F25: 비유동 리스부채 | G25: Non-current lease liability | I25: monetaryItemType | J25: INSTANT
B26: [D832620] 14. 리스부채 | 14. Lease liabilities | C26: 리스부채 분류에 대한 공시 | D26: entity00825959 | E26: LeaseLiabilityOfDisclosureOnTheClassificationOfLeaseLiabilitiesLineItemsOfDisclosureOnTheClassificationOfLeaseLiabilitiesTableOfItems | F26: 리스부채 합계 | G26: Total of lease liability | H26: totalLabel | I26: monetaryItemType | J26: INSTANT
B27: [D832620] 14. 리스부채 | 14. Lease liabilities | C27: 리스와 관련하여 당기손익으로 인식한 금액에 대한 공시 | D27: entity00825959 | E27: ImpairmentLossOnRightOfUseAssetsOfDisclosureOfAmountsRecognizedInProfitOrLossInRelationToLeasesOfDisclosureOfAmountsRecognizedInProfitOrLossInRelationToLeasesTableOfItems | F27: 사용권자산손상차손 | G27: Impairment loss on right‑of‑use assets | I27: monetaryItemType | J27: DURATION
B28: [D823180] 15. 무형자산 | 15. Intangible assets | C28: 무형자산 장부금액에 대한 공시 | D28: entity00825959 | E28: DisclosureOfTheCarryingAmountOfIntangibleAssetsAbstract | F28: 무형자산 장부금액에 대한 공시[ 개요 ] | G28: Disclosure of the carrying amount of intangible assets[ abstract ] | I28: stringItemType | J28: DURATION
B29: [D822390] 16. 금융자산 | 16. Financial assets | C29: 당기손익인식금융자산의 공시 | D29: entity00825959 | E29: DescriptionOfFinancialAssetsMeasuredAtFairValueThroughProfitOrLossOfDisclosureOfFinancialAssetsLineItemsOfDisclosureOfFinancialAssetsTableOfItems | F29: 당기손익공정가치측정금융자산에 대한 설명 | G29: Description of financial assets measured at fair value through profit or loss | I29: stringItemType | J29: DURATION
B30: [D822390] 16. 금융자산 | 16. Financial assets | C30: 기타포괄손익인식금융자산의 공시 | D30: entity00825959 | E30: DescriptionOfFinancialAssetsMeasuredAtFairValueThroughOtherComprehensiveIncomeOfDisclosureOfDetailedInformationAboutFinancialInstrumentsLineItemsOfDisclosureOfFinancialInstrumentsTableOfItems | F30: 기타포괄손익공정가치측정금융자산에 대한 설명 | G30: Description of financial assets measured at fair value through other comprehensive income | I30: stringItemType | J30: DURATION
B31: [D822460] 18. 매입채무 및 기타채무 | 18. Trade and other payables | C31: 공급자금융약정에 해당하는 금융부채 공시 | D31: entity00825959 | E31: LiabilitiesUnderSupplierFinancingArrangementsOfDisclosureOfFinancialLiabilitiesThatArePartOfSupplierFinanceArrangementsLineItemsOfDisclosureOfFinancialLiabilitiesThatArePartOfSupplierFinanceArrangementsTableOfItems | F31: 금융기관이 공급자에게 대금을 지급한 공급자금융약정 부채 | G31: Liabilities under supplier financing arrangements | I31: monetaryItemType | J31: INSTANT
B32: [D822400] 19. 단기차입금 | 19. Short-term borrowings | C32: 단기차입금의 상세내역 | D32: entity00825959 | E32: ExplanationOfCollateralProvidedInRelationToBorrowingsOfDisclosureOfDetailedInformationAboutBorrowingsLineItemsOfDetailedInformationAboutBorrowingsTableOfItems | F32: 차입금 관련 담보제공에 대한 설명 | G32: Explanation of collateral provided in relation to borrowings | I32: stringItemType | J32: DURATION
B33: [D861200] 22. 자본 | 22. Equity | C33: 자본을 구성하는 적립금에 대한 공시 [표] | D33: entity00825959 | E33: GainOnRepurchaseOfConversionRightsOfDisclosureOfReservesWithinEquityLineItemsOfDisclosureOfReservesWithinEquityTableOfItems | F33: 전환권재매입이익 | G33: Gain on repurchase of conversion rights | I33: monetaryItemType | J33: INSTANT
B34: [D861200] 22. 자본 | 22. Equity | C34: 자기주식 처분에 대한 공시 | D34: entity00825959 | E34: PreTaxGainOnDisposalOfTreasurySharesOfDisclosureOfDisposalOfTreasurySharesLineItemsOfDisclosureOfDisposalOfTreasurySharesTableOfItems | F34: 자기주식처분이익(세전) | G34: Pre‑tax gain on disposal of treasury shares | I34: monetaryItemType | J34: DURATION
B35: [D861200] 22. 자본 | 22. Equity | C35: 자기주식 처분에 대한 공시 | D35: entity00825959 | E35: PreTaxLossOnDisposalOfTreasurySharesOfDisclosureOfDisposalOfTreasurySharesLineItemsOfDisclosureOfDisposalOfTreasurySharesTableOfItems | F35: 자기주식처분손실(세전) | G35: Pre‑tax loss on disposal of treasury shares | I35: monetaryItemType | J35: DURATION
B36: [D834120] 23. 주식기준보상 | 23. Share-based payment arrangements | C36: 주식기준보상약정의 조건에 대한 공시 [표] | D36: entity00825959 | E36: NameOfTheGrantingCompanyOfDisclosureOfTermsAndConditionsOfShareBasedPaymentArrangementLineItemsOfDisclosureOfTermsAndConditionsOfSharebasedPaymentArrangementTableOfItems | F36: 부여회사명 | G36: Name of the granting company | I36: stringItemType | J36: DURATION
B37: [D834120] 23. 주식기준보상 | 23. Share-based payment arrangements | C37: 주식기준보상약정의 조건에 대한 공시 [표] | D37: entity00825959 | E37: ExplanationOfFairValuePerShareOfDisclosureOfTermsAndConditionsOfShareBasedPaymentArrangementLineItemsOfDisclosureOfTermsAndConditionsOfSharebasedPaymentArrangementTableOfItems | F37: 주당 공정가치에 대한 설명 | G37: Explanation of fair value per share | I37: stringItemType | J37: DURATION
B38: [D834120] 23. 주식기준보상 | 23. Share-based payment arrangements | C38: 주식선택권 내역의 공시 | D38: entity00825959 | E38: GrantRecipientsStockOptionOfDisclosureOfTermsAndConditionsOfStockOptionLineItemsOfDisclosureOfTermsAndConditionsOfStockOptionTableOfItems | F38: 부여대상, 주식선택권 | G38: Grant recipients, stock option | I38: stringItemType | J38: DURATION
B39: [D834120] 23. 주식기준보상 | 23. Share-based payment arrangements | C39: 보고기간 중 발생한 보상원가의 공시 | D39: entity00825959 | E39: CumulativeCompensationExpenseStockOptionsOfDisclosureOfCompensationCostsIncurredDuringTheReportingPeriodLineItemsOfDisclosureOfCompensationCostsIncurredDuringTheReportingPeriodTableOfItems | F39: 기초 누적보상비용, 주식선택권 | G39: Beginning of cumulative compensation expense at beginning of period, stock options | H39: periodStartLabel | I39: monetaryItemType | J39: INSTANT
B40: [D834120] 23. 주식기준보상 | 23. Share-based payment arrangements | C40: 보고기간 중 발생한 보상원가의 공시 | D40: entity00825959 | E40: CumulativeCompensationExpenseStockOptionsOfDisclosureOfCompensationCostsIncurredDuringTheReportingPeriodLineItemsOfDisclosureOfCompensationCostsIncurredDuringTheReportingPeriodTableOfItems | F40: 기말 누적보상비용, 주식선택권 | G40: Beginning of cumulative compensation expense at end of period, stock options | H40: periodEndLabel | I40: monetaryItemType | J40: INSTANT
B41: [D861310] 24. 배당금 | 24. Dividends | C41: 배당금에 대한 공시 [표] | D41: entity00825959 | E41: TypeOfDividendOfDisclosureOfDividendsPaidLineItemsOfDisclosureOfDividendsPaidTableOfItems | F41: 배당형식 | G41: Type of dividend | I41: stringItemType | J41: DURATION
B42: [D861310] 24. 배당금 | 24. Dividends | C42: 배당금에 대한 공시 [표] | D42: entity00825959 | E42: DividendRecordDateOfDisclosureOfDividendsPaidLineItemsOfDisclosureOfDividendsPaidTableOfItems | F42: 배당기준일 | G42: Dividend record date | I42: stringItemType | J42: DURATION
B43: [D861310] 24. 배당금 | 24. Dividends | C43: 배당금에 대한 공시 [표] | D43: entity00825959 | E43: DividendPayoutRatioOfDisclosureOfDividendsPaidLineItemsOfDisclosureOfDividendsPaidTableOfItems | F43: 배당성향 | G43: Dividend payout ratio | I43: percentItemType | J43: INSTANT
B44: [D861310] 24. 배당금 | 24. Dividends | C44: 배당금에 대한 공시 [표] | D44: entity00825959 | E44: DividendYieldOfDisclosureOfDividendsPaidLineItemsOfDisclosureOfDividendsPaidTableOfItems | F44: 배당수익률 | G44: Dividend yield | I44: percentItemType | J44: INSTANT
B45: [D834320] 26. 기타수익 및 기타비용 | 26. Other income and expense | C45: 기타수익 및 기타비용 [표] | D45: entity00825959 | E45: OtherRevenuesOfOtherIncomeAndExpensesLineItemsOfOtherIncomeAndExpensesTableOfItems | F45: 기타수입 | G45: Other revenues | I45: monetaryItemType | J45: DURATION
B46: [D834320] 26. 기타수익 및 기타비용 | 26. Other income and expense | C46: 기타수익 및 기타비용 [표] | D46: entity00825959 | E46: GainOnLeaseTerminationOfOtherIncomeAndExpensesLineItemsOfOtherIncomeAndExpensesTableOfItems | F46: 리스해지이익 | G46: Gain on lease termination | I46: monetaryItemType | J46: DURATION
B47: [D834320] 26. 기타수익 및 기타비용 | 26. Other income and expense | C47: 기타수익 및 기타비용 [표] | D47: entity00825959 | E47: ImpairmentLossOnRightOfUseAssetsOfOtherIncomeAndExpensesLineItemsOfOtherIncomeAndExpensesTableOfItems | F47: 사용권자산손상차손 | G47: Impairment loss on right-of-use assets | I47: monetaryItemType | J47: DURATION
B48: [D834300] 28. 비용의 성격별 분류 | 28. Expenses by nature | C48: 비용의 성격별 분류 공시 [표] | D48: entity00825959 | E48: ExplanationOfTheTotalsByNatureOfExpenseOfExpenseByNatureLineItemsOfExpenseByNatureTableOfItems | F48: 비용의 성격별 분류 합계에 대한 설명 | G48: Explanation of the totals by nature of expense | I48: stringItemType | J48: DURATION
B49: [D835110] 29. 법인세 | 29. Income taxes | C49: 법인세비용(수익)의 주요 구성요소 [표] | D49: entity00825959 | E49: TaxEffectOfTheExerciseOfStockOptionsOfCurrentTaxExpenseIncomeAndAdjustmentsForCurrentTaxOfPriorPeriodsLineItemsOfMajorComponentsOfTaxExpenseIncomeTableOfItems | F49: 주식선택권 행사로 인한 법인세효과 | G49: Tax effect of the exercise of stock options. | I49: monetaryItemType | J49: DURATION
B50: [D835110] 29. 법인세 | 29. Income taxes | C50: 회계이익에 적용세율을 곱하여 산출한 금액에 대한 조정 [표] | D50: entity00825959 | E50: TaxCreditsOfReconciliationOfAccountingProfitMultipliedByApplicableTaxRatesLineItemsOfReconciliationOfAccountingProfitMultipliedByApplicableTaxRatesTableOfItems | F50: 세액공제 | G50: Tax credits | H50: negatedLabel | I50: monetaryItemType | J50: DURATION
B51: [D835110] 29. 법인세 | 29. Income taxes | C51: 회계이익에 적용세율을 곱하여 산출한 금액에 대한 조정 [표] | D51: entity00825959 | E51: DeferredCorporateIncomeTaxEffectsRelatedToShareBasedPaymentsOfReconciliationOfAccountingProfitMultipliedByApplicableTaxRatesLineItemsOfReconciliationOfAccountingProfitMultipliedByApplicableTaxRatesTableOfItems | F51: 주식기준보상 이연법인세효과 | G51: Deferred corporate income tax effects related to share-based payments. | I51: monetaryItemType | J51: DURATION
B52: [D835110] 29. 법인세 | 29. Income taxes | C52: 회계이익에 적용세율을 곱하여 산출한 금액에 대한 조정 [표] | D52: entity00825959 | E52: TotalOfTaxEffectsForReconciliationBetweenAccountingProfitAndTaxExpenseIncomeOfReconciliationOfAccountingProfitMultipliedByApplicableTaxRatesLineItemsOfReconciliationOfAccountingProfitMultipliedByApplicableTaxRatesTableOfItems | F52: 회계이익과 법인세비용(수익)간의 조정에 대한 법인세효과 합계 | G52: Total of tax effects for reconciliation between accounting profit and tax expense (income) | H52: totalLabel | I52: monetaryItemType | J52: DURATION
B53: [D835110] 29. 법인세 | 29. Income taxes | C53: 자본에 직접 가감되는 항목과 관련된 당기법인세와 이연법인세 [표] | D53: entity00825959 | E53: CorporateTaxRelatingToItemsCreditedChargedDirectlyToEquityBeforeTaxGainsLossesOnTreasurySharesOfCurrentAndDeferredTaxRelatingToItemsCreditedChargedDirectlyToEquityLineItemsOfCurrentAndDeferredTaxRelatingToItemsChargedOrCreditedDirectlyToEquityTableOfItems | F53: 자본에 직접 반영한 법인세(세전), 자기주식 | G53: Corporate tax relating to items credited (charged) directly to equity, before tax, gains (losses) on treasury shares | I53: monetaryItemType | J53: DURATION
B54: [D835110] 29. 법인세 | 29. Income taxes | C54: 자본에 직접 가감되는 항목과 관련된 당기법인세와 이연법인세 [표] | D54: entity00825959 | E54: CorporateTaxRelatingToItemsCreditedChargedDirectlyToEquityBeforeTaxGainsLossesOnStockOptionsOfCurrentAndDeferredTaxRelatingToItemsCreditedChargedDirectlyToEquityLineItemsOfCurrentAndDeferredTaxRelatingToItemsChargedOrCreditedDirectlyToEquityTableOfItems | F54: 자본에 직접 반영한 법인세(세전), 주식선택권 | G54: Corporate tax relating to items credited (charged) directly to equity, before tax, gains (losses) on stock options | I54: monetaryItemType | J54: DURATION
B55: [D835110] 29. 법인세 | 29. Income taxes | C55: 자본에 직접 가감되는 항목과 관련된 당기법인세와 이연법인세 [표] | D55: entity00825959 | E55: GainLossRecognizedDirectlyInEquityBeforeTaxOfCurrentAndDeferredTaxRelatingToItemsCreditedChargedDirectlyToEquityLineItemsOfCurrentAndDeferredTaxRelatingToItemsChargedOrCreditedDirectlyToEquityTableOfItems | F55: 자본에 직접 반영한 손익(세전) 합계 | G55: Total of Gain (loss) recognized directly in equity (before tax) | H55: totalLabel | I55: monetaryItemType | J55: DURATION
B56: [D835110] 29. 법인세 | 29. Income taxes | C56: 자본에 직접 가감되는 항목과 관련된 당기법인세와 이연법인세 [표] | D56: entity00825959 | E56: IncomeTaxRelatingToTreasurySharesCreditedChargedDirectlyToEquityOfCurrentAndDeferredTaxRelatingToItemsCreditedChargedDirectlyToEquityLineItemsOfCurrentAndDeferredTaxRelatingToItemsChargedOrCreditedDirectlyToEquityTableOfItems | F56: 자본에 직접 반영한, 자기주식에 관련되는 법인세 | G56: Income tax relating to treasury shares credited (charged) directly to equity | I56: monetaryItemType | J56: DURATION
B57: [D835110] 29. 법인세 | 29. Income taxes | C57: 자본에 직접 가감되는 항목과 관련된 당기법인세와 이연법인세 [표] | D57: entity00825959 | E57: IncomeTaxRelatingToStockOptionsCreditedChargedDirectlyToEquityOfCurrentAndDeferredTaxRelatingToItemsCreditedChargedDirectlyToEquityLineItemsOfCurrentAndDeferredTaxRelatingToItemsChargedOrCreditedDirectlyToEquityTableOfItems | F57: 자본에 직접 반영한, 주식선택권에 관련되는 법인세 | G57: Income tax relating to stock options credited (charged) directly to equity | I57: monetaryItemType | J57: DURATION
B58: [D835110] 29. 법인세 | 29. Income taxes | C58: 자본에 직접 가감되는 항목과 관련된 당기법인세와 이연법인세 [표] | D58: entity00825959 | E58: CorporateTaxRelatingToItemsCreditedChargedDirectlyToEquityNetOfTaxGainsLossesOnTreasurySharesOfCurrentAndDeferredTaxRelatingToItemsCreditedChargedDirectlyToEquityLineItemsOfCurrentAndDeferredTaxRelatingToItemsChargedOrCreditedDirectlyToEquityTableOfItems | F58: 자본에 직접 반영한 법인세(세후), 자기주식 | G58: Corporate tax relating to items credited (charged) directly to equity, net of tax, gains (losses) on treasury shares | I58: monetaryItemType | J58: DURATION
B59: [D835110] 29. 법인세 | 29. Income taxes | C59: 자본에 직접 가감되는 항목과 관련된 당기법인세와 이연법인세 [표] | D59: entity00825959 | E59: CorporateTaxRelatingToItemsCreditedChargedDirectlyToEquityNetOfTaxGainsLossesOnStockOptionsOfCurrentAndDeferredTaxRelatingToItemsCreditedChargedDirectlyToEquityLineItemsOfCurrentAndDeferredTaxRelatingToItemsChargedOrCreditedDirectlyToEquityTableOfItems | F59: 자본에 직접 반영한 법인세(세후), 주식선택권 | G59: Corporate tax relating to items credited (charged) directly to equity, net of tax, gains (losses) on stock options | I59: monetaryItemType | J59: DURATION
B60: [D835110] 29. 법인세 | 29. Income taxes | C60: 자본에 직접 가감되는 항목과 관련된 당기법인세와 이연법인세 [표] | D60: entity00825959 | E60: GainLossRecognizedDirectlyInEquityAfterTaxOfCurrentAndDeferredTaxRelatingToItemsCreditedChargedDirectlyToEquityLineItemsOfCurrentAndDeferredTaxRelatingToItemsChargedOrCreditedDirectlyToEquityTableOfItems | F60: 자본에 직접 반영한 손익(세후) 합계 | G60: Total of Gain (loss) recognized directly in equity (after tax) | H60: totalLabel | I60: monetaryItemType | J60: DURATION
B61: [D838000] 30. 주당손익 | 30. Earnings per share | C61: 주당이익 [표] | D61: entity00825959 | E61: ExplanationOfCalculationDilutedEarningsPerShare | F61: 희석주당이익의 계산에 대한 기술 | G61: Explanation of calculation diluted earnings per share | I61: stringItemType | J61: DURATION
B62: [D851100] 31. 현금흐름표 | 31. Cash flow statement | C62: 영업활동 현금흐름 조정내역의 공시 | D62: entity00825959 | E62: AdjustmentsForCostOfSalesFromSaleOfGoodsProductOfCashFlowsFromUsedInOperatingActivitiesLineItemsOfCashFlowsFromUsedInOperatingActivitiesTableOfItems | F62: 제품매출원가 조정 | G62: Adjustments for cost of sales from sale of goods product | I62: monetaryItemType | J62: DURATION
B63: [D851100] 31. 현금흐름표 | 31. Cash flow statement | C63: 영업활동 현금흐름 조정내역의 공시 | D63: entity00825959 | E63: AdjustmentsForSalariesWagesOfCashFlowsFromUsedInOperatingActivitiesLineItemsOfCashFlowsFromUsedInOperatingActivitiesTableOfItems | F63: 급여 조정 | G63: Adjustments for salaries wages | I63: monetaryItemType | J63: DURATION
B64: [D851100] 31. 현금흐름표 | 31. Cash flow statement | C64: 영업활동 현금흐름 조정내역의 공시 | D64: entity00825959 | E64: AdjustmentsForResearchAndDevelopmentExpensesOfCashFlowsFromUsedInOperatingActivitiesLineItemsOfCashFlowsFromUsedInOperatingActivitiesTableOfItems | F64: 경상개발비 조정 | G64: Adjustments for research and development expenses | I64: monetaryItemType | J64: DURATION
B65: [D851100] 31. 현금흐름표 | 31. Cash flow statement | C65: 영업활동 현금흐름 조정내역의 공시 | D65: entity00825959 | E65: AdjustmentsForGainsFromGuaranteeOfCashFlowsFromUsedInOperatingActivitiesLineItemsOfCashFlowsFromUsedInOperatingActivitiesTableOfItems | F65: 보증수익 조정 | G65: Adjustments for gains from guarantee | H65: negatedLabel | I65: monetaryItemType | J65: DURATION
B66: [D851100] 31. 현금흐름표 | 31. Cash flow statement | C66: 현금의 유입과 유출이 없는 거래 중 중요한 사항의 공시 | D66: entity00825959 | E66: AppropriationOfRetainedEarningsOfDisclosureOfSignificantTransactionsNotRequireUseOfCashOrCashEquivalentsLineItemsOfDisclosureOfSignificantTransactionsNotRequireUseOfCashOrCashEquivalentsTableOfItems | F66: 이익준비금 적립 | G66: Appropriation of retained earnings | I66: monetaryItemType | J66: INSTANT
B67: [D851100] 31. 현금흐름표 | 31. Cash flow statement | C67: 현금의 유입과 유출이 없는 거래 중 중요한 사항의 공시 | D67: entity00825959 | E67: ReclassificationOfDepositsToCurrentAssetsOfDisclosureOfSignificantTransactionsNotRequireUseOfCashOrCashEquivalentsLineItemsOfDisclosureOfSignificantTransactionsNotRequireUseOfCashOrCashEquivalentsTableOfItems | F67: 보증금 유동성대체 | G67: Reclassification of deposits to current assets | I67: monetaryItemType | J67: INSTANT
B68: [D851100] 31. 현금흐름표 | 31. Cash flow statement | C68: 현금의 유입과 유출이 없는 거래 중 중요한 사항의 공시 | D68: entity00825959 | E68: ReclassificationOfTradeReceivablesToOtherReceivablesOfDisclosureOfSignificantTransactionsNotRequireUseOfCashOrCashEquivalentsLineItemsOfDisclosureOfSignificantTransactionsNotRequireUseOfCashOrCashEquivalentsTableOfItems | F68: 매출채권 미수금 대체 | G68: Reclassification of trade receivables to other receivables | I68: monetaryItemType | J68: INSTANT
B69: [D851100] 31. 현금흐름표 | 31. Cash flow statement | C69: 현금의 유입과 유출이 없는 거래 중 중요한 사항의 공시 | D69: entity00825959 | E69: ReclassificationOfLeaseLiabilitiesToCurrentLiabilitiesOfDisclosureOfSignificantTransactionsNotRequireUseOfCashOrCashEquivalentsLineItemsOfDisclosureOfSignificantTransactionsNotRequireUseOfCashOrCashEquivalentsTableOfItems | F69: 리스부채 유동성대체 | G69: Reclassification of lease liabilities to current liabilities | I69: monetaryItemType | J69: INSTANT
B70: [D851100] 31. 현금흐름표 | 31. Cash flow statement | C70: 현금의 유입과 유출이 없는 거래 중 중요한 사항의 공시 | D70: entity00825959 | E70: ShareSwapTransactionInvolvingTreasurySharesOfDisclosureOfSignificantTransactionsNotRequireUseOfCashOrCashEquivalentsLineItemsOfDisclosureOfSignificantTransactionsNotRequireUseOfCashOrCashEquivalentsTableOfItems | F70: 자기주식 교환거래 | G70: Share swap transaction involving treasury shares | I70: monetaryItemType | J70: INSTANT
B71: [D851100] 31. 현금흐름표 | 31. Cash flow statement | C71: 재무활동에서 생기는 부채의 조정에 관한 공시 [표] | D71: entity00825959 | E71: IncreaseDecreaseThroughInterestExpenseLiabilitiesArisingFromFinancingActivitiesOfDisclosureOfReconciliationOfLiabilitiesArisingFromFinancingActivitiesLineItemsOfDisclosureOfReconciliationOfLiabilitiesArisingFromFinancingActivitiesTableOfItems | F71: 이자비용, 재무활동에서 생기는 부채의 증가(감소) | G71: Increase (decrease) through interest expense, liabilities arising from financing activities | I71: monetaryItemType | J71: DURATION
B72: [D818000] 32. 특수관계자 거래 | 32. Related party transactions | C72: 특수관계자거래에 대한 공시 [표] | D72: entity00825959 | E72: DividendIncomeRelatedPartyTransactionsOfDisclosureOfTransactionsBetweenRelatedPartiesLineItemsOfDisclosureOfTransactionsBetweenRelatedPartiesTableOfItems | F72: 배당금수입, 특수관계자거래 | G72: Dividend income, related party transactions | I72: monetaryItemType | J72: DURATION
B73: [D818000] 32. 특수관계자 거래 | 32. Related party transactions | C73: 특수관계자거래에 대한 공시 [표] | D73: entity00825959 | E73: RentalIncomeAndOthersRelatedPartyTransactionsOfDisclosureOfTransactionsBetweenRelatedPartiesLineItemsOfDisclosureOfTransactionsBetweenRelatedPartiesTableOfItems | F73: 수입임대료 등, 특수관계자거래 | G73: Rental income and others, related party transactions | I73: monetaryItemType | J73: DURATION
B74: [D818000] 32. 특수관계자 거래 | 32. Related party transactions | C74: 특수관계자거래의 채권·채무 잔액에 대한 공시 [표] | D74: entity00825959 | E74: GuaranteeDepositRentRelatedPartyTransactionsOfDisclosureOfOutstandingBalancesForRelatedPartyTransactionsLineItemsOfDisclosureOfOutstandingBalancesForRelatedPartyTransactionsTableOfItems | F74: 임대보증금, 특수관계자거래 | G74: Guarantee deposit rent, related party transactions | I74: monetaryItemType | J74: DURATION
B75: [D818000] 32. 특수관계자 거래 | 32. Related party transactions | C75: 특수관계자거래의 채권·채무 잔액에 대한 공시 [표] | D75: entity00825959 | E75: LoansRelatedPartyTransactionsOfDisclosureOfOutstandingBalancesForRelatedPartyTransactionsLineItemsOfDisclosureOfOutstandingBalancesForRelatedPartyTransactionsTableOfItems | F75: 대여금, 특수관계자거래 | G75: Loans, related party transactions | I75: monetaryItemType | J75: DURATION
B76: [D818000] 32. 특수관계자 거래 | 32. Related party transactions | C76: 특수관계자 자금거래에 관한 공시 [표] | D76: entity00825959 | E76: DisclosureOfGuaranteesOrCollateralInvolvingRelatedParties | F76: 특수관계자 보증 또는 담보의 공시 | G76: Disclosure of guarantees or collateral involving related parties | I76: stringItemType | J76: DURATION
B77: [D827580] 33. 약정사항 및 우발사항 | 33. Commitments and contingencies | C77: 담보로 제공된 자산에 대한 공시 | D77: entity00825959 | E77: MaximumMortgageOfDisclosureOfAssetsPledgedAsSecurityLineItemsOfDisclosureOfAssetsPledgedAsSecurityTableOfItems | F77: 근저당권 | G77: Maximum mortgage | I77: monetaryItemType | J77: INSTANT
... B92: [D520005] 현금흐름표, 간접법 - 별도 | Statement of cash flows, indirect method - Separate financial statements | C92: 현금흐름표, 간접법 - 별도 | D92: entity00825959 | E92: IncreaseInGuaranteeDepositsAsInvestingActivitiesOfCashFlowsFromUsedInInvestingActivities | F92: 임대보증금의 증가 | G92: Increase in guarantee deposits as investing activities | I92: monetaryItemType | J92: DURATION
B93: [D520005] 현금흐름표, 간접법 - 별도 | Statement of cash flows, indirect method - Separate financial statements | C93: 현금흐름표, 간접법 - 별도 | D93: entity00825959 | E93: DecreaseInGuaranteeDepositsAsInvestingActivitiesOfCashFlowsFromUsedInInvestingActivities | F93: 임대보증금의 감소 | G93: Decrease in guarantee deposits as investing activities | H93: negatedLabel | I93: monetaryItemType | J93: DURATION
B94: [D822105] 11. 유형자산 | 11. Property, plant and equipment | C94: 담보제공 유형자산에 대한 공시 | D94: entity00825959 | E94: DescriptionOfPropertyPlantAndEquipmentPledgedAsCollateralOfDisclosureOfPropertyPlantAndEquipmentPledgedAsCollateralLineItemsOfDisclosureOfPropertyPlantAndEquipmentPledgedAsCollateralTableOfItems | F94: 담보제공 유형자산에 대한 설명 | G94: Description of property, plant and equipment pledged as collateral | I94: stringItemType | J94: DURATION
B95: [D825105] 12. 투자부동산 | 12. Investment property | C95: 투자부동산에 대한 세부 정보 공시 [표] | D95: entity00825959 | E95: DescriptionOfTransfersOfInvestmentPropertyOfDisclosureOfDetailedInformationAboutInvestmentPropertyLineItemsOfDisclosureOfInvestmentPropertyTableOfItems | F95: 투자부동산 대체에 대한 설명 | G95: Description of transfers of investment property | I95: stringItemType | J95: DURATION
B96: [D825105] 12. 투자부동산 | 12. Investment property | C96: 투자부동산 총장부금액, 감가상각누계액 변동에 대한 공시 | D96: entity00825959 | E96: DescriptionOfTransfersOfInvestmentPropertyOfDisclosureOfChangesInTheGrossCarryingAmountOfInvestmentPropertyAndAccumulatedDepreciationLineItemsOfDisclosureOfChangeInTheGrossCarryingAmountOfInvestmentPropertyAndAccumulatedDepreciationTableOfItems | F96: 투자부동산 대체에 대한 설명 | G96: Description of transfers of investment property | I96: stringItemType | J96: DURATION
B97: [D832615] 13. 사용권자산 | 13. Right-of-use assets | C97: 13. 사용권자산 | D97: entity00825959 | E97: InformationAboutTheNatureOfLeasingActivities | F97: 리스활동 특성에 대한 정보 | G97: Information about the nature of leasing activities | I97: stringItemType | J97: DURATION
B98: [D832625] 14. 리스부채 | 14. Lease liabilities | C98: 리스부채 분류에 대한 공시 | D98: entity00825959 | E98: DisclosureOnTheClassificationOfLeaseLiabilityAbstract | F98: 리스부채 분류에 대한 공시[ 개요 ] | G98: Disclosure on the classification of lease liability[ abstract ] | I98: stringItemType | J98: DURATION
B99: [D832625] 14. 리스부채 | 14. Lease liabilities | C99: 리스부채 분류에 대한 공시 | D99: entity00825959 | E99: DisclosureOnTheClassificationOfLeaseLiabilityLineItemsOfDisclosureOnTheClassificationOfLeaseLiabilityTableOfLineItems | F99: 리스부채 분류에 대한 공시 [ 항목 ] | G99: Disclosure on the classification of lease liability [line items] | I99: stringItemType | J99: DURATION
B100: [D832625] 14. 리스부채 | 14. Lease liabilities | C100: 리스부채 분류에 대한 공시 | D100: entity00825959 | E100: CurrentLeaseLiabilityOfDisclosureOnTheClassificationOfLeaseLiabilityLineItemsOfDisclosureOnTheClassificationOfLeaseLiabilityTableOfItems | F100: 유동 리스부채 | G100: Current lease liability | I100: monetaryItemType | J100: INSTANT
B101: [D832625] 14. 리스부채 | 14. Lease liabilities | C101: 리스부채 분류에 대한 공시 | D101: entity00825959 | E101: NonCurrentLeaseLiabilityOfDisclosureOnTheClassificationOfLeaseLiabilityLineItemsOfDisclosureOnTheClassificationOfLeaseLiabilityTableOfItems | F101: 비유동 리스부채 | G101: Non-current lease liability | I101: monetaryItemType | J101: INSTANT
B102: [D832625] 14. 리스부채 | 14. Lease liabilities | C102: 리스부채 분류에 대한 공시 | D102: entity00825959 | E102: LeaseLiabilityOfDisclosureOnTheClassificationOfLeaseLiabilityLineItemsOfDisclosureOnTheClassificationOfLeaseLiabilityTableOfItems | F102: 리스부채 합계 | G102: Total of Lease liability | H102: totalLabel | I102: monetaryItemType | J102: INSTANT
B103: [D823185] 15. 무형자산 | 15. Intangible assets | C103: 무형자산 장부금액에 대한 공시 | D103: entity00825959 | E103: DisclosureOfTheCarryingAmountOfIntangibleAssetAbstract | F103: 무형자산 장부금액에 대한 공시[ 개요 ] | G103: Disclosure of the carrying amount of intangible asset[ abstract ] | I103: stringItemType | J103: DURATION
B104: [D823185] 15. 무형자산 | 15. Intangible assets | C104: 무형자산 장부금액에 대한 공시 | D104: entity00825959 | E104: DisclosureOfTheCarryingAmountOfIntangibleAssetLineItemsOfDisclosureOfTheCarryingAmountOfIntangibleAssetTableOfLineItems | F104: 무형자산 장부금액에 대한 공시 [ 항목 ] | G104: Disclosure of the carrying amount of intangible asset [line items] | I104: stringItemType | J104: DURATION
B105: [D822395] 16. 금융자산 | 16. Financial assets | C105: 당기손익인식금융자산의 공시 | D105: entity00825959 | E105: DescriptionOfFinancialAssetsMeasuredAtFairValueThroughProfitOrLossOfDisclosureOfFinancialAssetsLineItemsOfDisclosureOfFinancialAssetsTableOfItems | F105: 당기손익공정가치측정금융자산에 대한 설명 | G105: Description of financial assets measured at fair value through profit or loss | I105: stringItemType | J105: DURATION
B106: [D822395] 16. 금융자산 | 16. Financial assets | C106: 기타포괄손익인식금융자산의 공시 | D106: entity00825959 | E106: DescriptionOfFinancialAssetsMeasuredAtFairValueThroughOtherComprehensiveIncomeOfDisclosureOfDetailedInformationAboutFinancialInstrumentsLineItemsOfDisclosureOfFinancialInstrumentsTableOfItems | F106: 기타포괄손익공정가치측정금융자산에 대한 설명 | G106: Description of financial assets measured at fair value through other comprehensive income | I106: stringItemType | J106: DURATION
B107: [D822465] 18. 매입채무 및 기타채무 | 18. Trade and other payables | C107: 공급자금융약정에 해당하는 금융부채 공시 | D107: entity00825959 | E107: LiabilitiesUnderSupplierFinancingArrangementsOfDisclosureOfFinancialLiabilitiesThatArePartOfSupplierFinanceArrangementsLineItemsOfDisclosureOfFinancialLiabilitiesThatArePartOfSupplierFinanceArrangementsTableOfItems | F107: 금융기관이 공급자에게 대금을 지급한 공급자금융약정 부채 | G107: Liabilities under supplier financing arrangements | I107: monetaryItemType | J107: INSTANT
B108: [D861205] 21. 자본 | 21. Equity | C108: 이익잉여금 처분계산서 | D108: entity00825959 | E108: ScheduledDateOfTheResolutionOnAppropriationOfRetainedEarningsOfStatementOfAppropriationOfRetainedEarningsLineItemsOfStatementOfAppropriationOfRetainedEarningsTableOfItems | F108: 이익잉여금 처분예정일 | G108: Scheduled date of the resolution on appropriation of retained earnings | I108: dateItemType | J108: DURATION
B109: [D861205] 21. 자본 | 21. Equity | C109: 이익잉여금 처분계산서 | D109: entity00825959 | E109: DateOnWhichTheResolutionOnAppropriationOfRetainedEarningsWasApprovedOfStatementOfAppropriationOfRetainedEarningsLineItemsOfStatementOfAppropriationOfRetainedEarningsTableOfItems | F109: 이익잉여금 처분확정일 | G109: Date on which the resolution on appropriation of retained earnings was approved | I109: dateItemType | J109: DURATION
B110: [D834125] 22. 주식기준보상 | 22. Share-based payment arrangements | C110: 주식기준보상약정의 조건에 대한 공시 [표] | D110: entity00825959 | E110: NameOfTheGrantingCompanyOfDisclosureOfTermsAndConditionsOfShareBasedPaymentArrangementLineItemsOfDisclosureOfTermsAndConditionsOfSharebasedPaymentArrangementTableOfItems | F110: 부여회사명 | G110: Name of the granting company | I110: stringItemType | J110: DURATION
B111: [D834125] 22. 주식기준보상 | 22. Share-based payment arrangements | C111: 주식기준보상약정의 조건에 대한 공시 [표] | D111: entity00825959 | E111: ExplanationOfFairValuePerShareOfDisclosureOfTermsAndConditionsOfShareBasedPaymentArrangementLineItemsOfDisclosureOfTermsAndConditionsOfSharebasedPaymentArrangementTableOfItems | F111: 주당 공정가치에 대한 설명 | G111: Explanation of fair value per share | I111: stringItemType | J111: DURATION
B112: [D861315] 23. 배당금 | 23. Dividends | C112: 배당금에 대한 공시 [표] | D112: entity00825959 | E112: TypeOfDividendOfDisclosureOfDividendsPaidLineItemsOfDisclosureOfDividendsPaidTableOfItems | F112: 배당형식 | G112: Type of dividend | I112: stringItemType | J112: DURATION
B113: [D861315] 23. 배당금 | 23. Dividends | C113: 배당금에 대한 공시 [표] | D113: entity00825959 | E113: DividendRecordDateOfDisclosureOfDividendsPaidLineItemsOfDisclosureOfDividendsPaidTableOfItems | F113: 배당기준일 | G113: Dividend record date | I113: stringItemType | J113: DURATION
B114: [D861315] 23. 배당금 | 23. Dividends | C114: 배당금에 대한 공시 [표] | D114: entity00825959 | E114: DividendPayoutRatioOfDisclosureOfDividendsPaidLineItemsOfDisclosureOfDividendsPaidTableOfItems | F114: 배당성향 | G114: Dividend payout ratio | I114: percentItemType | J114: INSTANT
... B118: [D834305] 27. 비용의 성격별 분류 | 27. Expenses by nature | C118: 비용의 성격별 분류 공시 [표] | D118: entity00825959 | E118: ExplanationOfTheTotalsByNatureOfExpenseOfExpenseByNatureLineItemsOfExpenseByNatureTableOfItems | F118: 비용의 성격별 분류 합계에 대한 설명 | G118: Explanation of the totals by nature of expense | I118: stringItemType | J118: DURATION
B119: [D835115] 28. 법인세 | 28. Income taxes | C119: 회계이익에 적용세율을 곱하여 산출한 금액에 대한 조정 [표] | D119: entity00825959 | E119: TaxCreditsOfReconciliationOfAccountingProfitMultipliedByApplicableTaxRatesLineItemsOfReconciliationOfAccountingProfitMultipliedByApplicableTaxRatesTableOfItems | F119: 세액공제 | G119: Tax credits | H119: negatedLabel | I119: monetaryItemType | J119: DURATION
B120: [D835115] 28. 법인세 | 28. Income taxes | C120: 회계이익에 적용세율을 곱하여 산출한 금액에 대한 조정 [표] | D120: entity00825959 | E120: DeferredCorporateIncomeTaxEffectsRelatedToShareBasedPaymentsOfReconciliationOfAccountingProfitMultipliedByApplicableTaxRatesLineItemsOfReconciliationOfAccountingProfitMultipliedByApplicableTaxRatesTableOfItems | F120: 주식기준보상 이연법인세효과 | G120: Deferred corporate income tax effects related to share-based payments. | I120: monetaryItemType | J120: DURATION
B121: [D835115] 28. 법인세 | 28. Income taxes | C121: 회계이익에 적용세율을 곱하여 산출한 금액에 대한 조정 [표] | D121: entity00825959 | E121: TotalOfTaxEffectsForReconciliationBetweenAccountingProfitAndTaxExpenseIncomeOfReconciliationOfAccountingProfitMultipliedByApplicableTaxRatesLineItemsOfReconciliationOfAccountingProfitMultipliedByApplicableTaxRatesTableOfItems | F121: 회계이익과 법인세비용(수익)간의 조정에 대한 법인세효과 합계 | G121: Total of tax effects for reconciliation between accounting profit and tax expense (income) | H121: totalLabel | I121: monetaryItemType | J121: DURATION
B122: [D835115] 28. 법인세 | 28. Income taxes | C122: 회계이익에 적용세율을 곱하여 산출한 금액에 대한 조정 [표] | D122: entity00825959 | E122: DescriptionsOfAverageEffectiveTaxRateOfReconciliationOfAccountingProfitMultipliedByApplicableTaxRatesLineItemsOfReconciliationOfAccountingProfitMultipliedByApplicableTaxRatesTableOfItems | F122: 평균유효세율에 대한 설명 | G122: Descriptions of average effective tax rate | I122: stringItemType | J122: DURATION
B123: [D835115] 28. 법인세 | 28. Income taxes | C123: 자본에 직접 가감되는 항목과 관련된 당기법인세와 이연법인세 [표] | D123: entity00825959 | E123: CorporateTaxRelatingToItemsCreditedChargedDirectlyToEquityBeforeTaxGainsLossesOnTreasurySharesOfCurrentAndDeferredTaxRelatingToItemsCreditedChargedDirectlyToEquityLineItemsOfCurrentAndDeferredTaxRelatingToItemsChargedOrCreditedDirectlyToEquityTableOfItems | F123: 자본에 직접 반영한 법인세(세전), 자기주식 | G123: Corporate tax relating to items credited (charged) directly to equity, before tax, gains (losses) on treasury shares | I123: monetaryItemType | J123: DURATION
B124: [D835115] 28. 법인세 | 28. Income taxes | C124: 자본에 직접 가감되는 항목과 관련된 당기법인세와 이연법인세 [표] | D124: entity00825959 | E124: CorporateTaxRelatingToItemsCreditedChargedDirectlyToEquityBeforeTaxOfCurrentAndDeferredTaxRelatingToItemsCreditedChargedDirectlyToEquityLineItemsOfCurrentAndDeferredTaxRelatingToItemsChargedOrCreditedDirectlyToEquityTableOfItems | F124: 자본에 직접 반영한 법인세(세전) 합계 | G124: Total of corporate tax relating to items credited (charged) directly to equity, before tax | H124: totalLabel | I124: monetaryItemType | J124: DURATION
B125: [D835115] 28. 법인세 | 28. Income taxes | C125: 자본에 직접 가감되는 항목과 관련된 당기법인세와 이연법인세 [표] | D125: entity00825959 | E125: IncomeTaxRelatingToTreasurySharesCreditedChargedDirectlyToEquityOfCurrentAndDeferredTaxRelatingToItemsCreditedChargedDirectlyToEquityLineItemsOfCurrentAndDeferredTaxRelatingToItemsChargedOrCreditedDirectlyToEquityTableOfItems | F125: 자본에 직접 반영한, 자기주식에 관련되는 법인세 | G125: Income tax relating to treasury shares credited (charged) directly to equity | I125: monetaryItemType | J125: DURATION
B126: [D835115] 28. 법인세 | 28. Income taxes | C126: 자본에 직접 가감되는 항목과 관련된 당기법인세와 이연법인세 [표] | D126: entity00825959 | E126: CorporateTaxRelatingToItemsCreditedChargedDirectlyToEquityNetOfTaxGainsLossesOnTreasurySharesOfCurrentAndDeferredTaxRelatingToItemsCreditedChargedDirectlyToEquityLineItemsOfCurrentAndDeferredTaxRelatingToItemsChargedOrCreditedDirectlyToEquityTableOfItems | F126: 자본에 직접 반영한 법인세(세후), 자기주식 | G126: Corporate tax relating to items credited (charged) directly to equity, net of tax, gains (losses) on treasury shares | I126: monetaryItemType | J126: DURATION
...

Sheet Checklist_7-1
B2: Negate 검토
B3: ※ XBRL Checklist 결과는 참고 목적으로 제공드리는 내역으로, 텍사노미 구조와 관련된 리뷰는 CoE 업무 Scope에 포함되지 않습니다.
B11: 28 | C11: 개 항목이 추출되었습니다.
B13: Role Definition | C13: TABLE NAME | D13: Prefix | E13: Name | F13: Label(KO) | G13: Label(EN) | H13: Label Role | I13: DataType | J13: Period | K13: Negate_표준 | L13: Negate_사용자지정
B14: [D610000] 자본변동표 - 연결 | Statement of changes in equity - Consolidated financial statements | C14: 자본변동표 [표] | D14: ifrs-full | E14: PurchaseOfTreasuryShares | F14: 자기주식의 취득 | G14: Purchase of treasury shares | H14: negatedLabel | I14: xbrli:monetaryItemType | J14: DURATION | K14: - | L14: negate
B15: [D826380] 9. 재고자산 | 9. Inventories | C15: 재고자산평가충당금 변동내역 | D15: ifrs-full | E15: InventoryWritedown2011 | F15: 재고자산 평가손실 | G15: Inventory write-down | H15: negatedLabel | I15: xbrli:monetaryItemType | J15: DURATION | K15: - | L15: negate
B16: [D826380] 9. 재고자산 | 9. Inventories | C16: 재고자산평가충당금 변동내역 | D16: entity00825959 | E16: RetirementsInventoriesOfMovementsInAllowanceForInventoryValuationLossesOfMovementsInAllowanceForInventoryValuationLossesTableOfItems | F16: 폐기, 재고자산 | G16: Retirements, inventories | H16: negatedLabel | I16: monetaryItemType | J16: DURATION | K16: - | L16: negate
B17: [D825100] 12. 투자부동산 | 12. Investment property | C17: 투자부동산에 대한 세부 정보 공시 [표] | D17: ifrs-full | E17: DepreciationInvestmentProperty | F17: 감가상각비, 투자부동산 | G17: Depreciation, investment property | H17: negatedLabel | I17: xbrli:monetaryItemType | J17: DURATION | K17: - | L17: negate
B18: [D825100] 12. 투자부동산 | 12. Investment property | C18: 투자부동산 총장부금액, 감가상각누계액 변동에 대한 공시 | D18: ifrs-full | E18: DepreciationInvestmentProperty | F18: 감가상각비, 투자부동산 | G18: Depreciation, investment property | H18: negatedLabel | I18: xbrli:monetaryItemType | J18: DURATION | K18: - | L18: negate
B19: [D832620] 14. 리스부채 | 14. Lease liabilities | C19: 리스부채에 대한 양적 정보 공시 [표] | D19: dart | E19: DecreaseDueToTerminationOrCancellationOfLeaseContractsLeaseLiabilities | F19: 계약 종료 또는 해지로 인한 감소, 리스부채 | G19: Decrease due to termination or cancellation of lease contracts lease liabilities | H19: negatedLabel | I19: xbrli:monetaryItemType | J19: DURATION | K19: - | L19: negate
B20: [D834480] 21. 퇴직급여제도 | 21. Employee benefit plans | C20: 확정급여제도에 대한 공시 [표] | D20: ifrs-full | E20: PlanAssetsAtFairValue | F20: 사외적립자산, 공정가치 | G20: Plan assets, at fair value | H20: negatedLabel | I20: xbrli:monetaryItemType | J20: INSTANT | K20: - | L20: negate
B21: [D861200] 22. 자본 | 22. Equity | C21: 자기주식의 변동내역 | D21: dart | E21: DispositionOfTreasuryShares | F21: 자기주식의 처분 | G21: Disposition of treasury shares | H21: negatedLabel | I21: xbrli:monetaryItemType | J21: DURATION | K21: - | L21: negate
B22: [D834120] 23. 주식기준보상 | 23. Share-based payment arrangements | C22: 주식선택권 상세내역의 공시 | D22: ifrs-full | E22: NumberOfShareOptionsExercisedInSharebasedPaymentArrangement | F22: 행사수량 (단위:주) | G22: Number of share options exercised in share-based payment arrangement(Unit:Share) | H22: negatedTerseLabel | I22: xbrli:decimalItemType | J22: DURATION | K22: - | L22: negate
B23: [D834120] 23. 주식기준보상 | 23. Share-based payment arrangements | C23: 주식선택권 상세내역의 공시 | D23: ifrs-full | E23: NumberOfShareOptionsExpiredInSharebasedPaymentArrangement | F23: 소멸수량 (단위:주) | G23: Number of share options expired in share-based payment arrangement (Unit:share) | H23: negatedTerseLabel | I23: xbrli:decimalItemType | J23: DURATION | K23: - | L23: negate
B24: [D835110] 29. 법인세 | 29. Income taxes | C24: 회계이익에 적용세율을 곱하여 산출한 금액에 대한 조정 [표] | D24: entity00825959 | E24: TaxCreditsOfReconciliationOfAccountingProfitMultipliedByApplicableTaxRatesLineItemsOfReconciliationOfAccountingProfitMultipliedByApplicableTaxRatesTableOfItems | F24: 세액공제 | G24: Tax credits | H24: negatedLabel | I24: monetaryItemType | J24: DURATION | K24: - | L24: negate
... B41: [D822385] 35. 위험관리 | 35. Risk management | C41: 부채비율 | D41: ifrs-full | E41: CashAndCashEquivalents | F41: 현금및현금성자산 | G41: Cash and cash equivalents | H41: negatedLabel | I41: xbrli:monetaryItemType | J41: INSTANT | K41: - | L41: negate
